{"type":"FeatureCollection","features":[{"type":"Feature","geometry":{"type":"Polygon","coordinates":[[[18.2179,48.1194],[18.2153,48.1183],[18.215,48.1192],[18.2179,48.1194]]]},"properties":{"Kateg\u00f3ria lesa":"H","V\u00fdmera v m2":21757.0,"OBJECTID":1117938}},{"type":"Feature","geometry":{"type":"Polygon","coordinates":[[[18.2152,48.1182],[18.2155,48.1174],[18.2128,48.1174],[18.2152,48.1182]],[[18.2126,48.1174],[18.2125,48.1178],[18.2137,48.118],[18.2126,48.1174]],[[18.2126,48.1174],[18.2133,48.1169],[18.2127,48.1168],[18.2126,48.1174]]]},"properties":{"Kateg\u00f3ria lesa":"H","V\u00fdmera v m2":19951.0,"OBJECTID":1117952}},{"type":"Feature","geometry":{"type":"Polygon","coordinates":[[[18.2185,48.1123],[18.2142,48.1117],[18.2139,48.1125],[18.2185,48.1123]]]},"properties":{"Kateg\u00f3ria lesa":"H","V\u00fdmera v m2":30315.0,"OBJECTID":1118119}},{"type":"Feature","geometry":{"type":"Polygon","coordinates":[[[18.2149,48.1156],[18.2131,48.1154],[18.2128,48.1166],[18.2149,48.1156]],[[18.2134,48.1168],[18.2127,48.1167],[18.2127,48.1168],[18.2134,48.1168]]]},"properties":{"Kateg\u00f3ria lesa":"H","V\u00fdmera v m2":18446.0,"OBJECTID":1118148}},{"type":"Feature","geometry":{"type":"Polygon","coordinates":[[[18.2324,48.135],[18.2318,48.1332],[18.232,48.1353],[18.2324,48.135]]]},"properties":{"Kateg\u00f3ria lesa":"H","V\u00fdmera v m2":4557.0,"OBJECTID":1118204}},{"type":"Feature","geometry":{"type":"Polygon","coordinates":[[[18.2173,48.1552],[18.2148,48.1545],[18.214,48.156],[18.2173,48.1552]]]},"properties":{"Kateg\u00f3ria lesa":"H","V\u00fdmera v m2":31156.0,"OBJECTID":1118221}},{"type":"Feature","geometry":{"type":"Polygon","coordinates":[[[18.2234,48.1622],[18.2184,48.1588],[18.219,48.1613],[18.2234,48.1622]]]},"properties":{"Kateg\u00f3ria lesa":"H","V\u00fdmera v m2":58204.0,"OBJECTID":1118301}},{"type":"Feature","geometry":{"type":"Polygon","coordinates":[[[18.2166,48.155],[18.2176,48.154],[18.2135,48.154],[18.2166,48.155]]]},"properties":{"Kateg\u00f3ria lesa":"H","V\u00fdmera v m2":32520.0,"OBJECTID":1118385}},{"type":"Feature","geometry":{"type":"Polygon","coordinates":[[[18.2092,48.1202],[18.2085,48.121],[18.2102,48.1213],[18.2092,48.1202]]]},"properties":{"Kateg\u00f3ria lesa":"H","V\u00fdmera v m2":12059.0,"OBJECTID":1118578}},{"type":"Feature","geometry":{"type":"Polygon","coordinates":[[[18.2318,48.1381],[18.2314,48.1396],[18.2321,48.1384],[18.2318,48.1381]],[[18.232,48.1371],[18.2318,48.1376],[18.2336,48.1382],[18.232,48.1371]]]},"properties":{"Kateg\u00f3ria lesa":"H","V\u00fdmera v m2":9959.0,"OBJECTID":1118585}},{"type":"Feature","geometry":{"type":"Polygon","coordinates":[[[18.2089,48.1196],[18.2062,48.1193],[18.2065,48.12],[18.2089,48.1196]]]},"properties":{"Kateg\u00f3ria lesa":"H","V\u00fdmera v m2":13020.0,"OBJECTID":1118596}},{"type":"Feature","geometry":{"type":"Polygon","coordinates":[[[18.1906,48.1278],[18.1939,48.1254],[18.1916,48.1248],[18.1906,48.1278]],[[18.1943,48.1254],[18.1942,48.1261],[18.1948,48.1255],[18.1943,48.1254]],[[18.1939,48.1264],[18.1933,48.1263],[18.1934,48.127],[18.1939,48.1264]]]},"properties":{"Kateg\u00f3ria lesa":"H","V\u00fdmera v m2":61805.0,"OBJECTID":1118607}},{"type":"Feature","geometry":{"type":"Polygon","coordinates":[[[18.2062,48.1192],[18.2066,48.1172],[18.2038,48.1168],[18.2062,48.1192]]]},"properties":{"Kateg\u00f3ria lesa":"H","V\u00fdmera v m2":34245.0,"OBJECTID":1118642}},{"type":"Feature","geometry":{"type":"Polygon","coordinates":[[[18.2193,48.1479],[18.2177,48.1473],[18.2164,48.1497],[18.2193,48.1479]]]},"properties":{"Kateg\u00f3ria lesa":"H","V\u00fdmera v m2":35096.0,"OBJECTID":1118777}},{"type":"Feature","geometry":{"type":"Polygon","coordinates":[[[18.2177,48.161],[18.2157,48.1628],[18.2172,48.1632],[18.2177,48.161]]]},"properties":{"Kateg\u00f3ria lesa":"H","V\u00fdmera v m2":25219.0,"OBJECTID":1118790}},{"type":"Feature","geometry":{"type":"Polygon","coordinates":[[[18.2263,48.1616],[18.2272,48.163],[18.2275,48.1619],[18.2263,48.1616]]]},"properties":{"Kateg\u00f3ria lesa":"H","V\u00fdmera v m2":7178.0,"OBJECTID":1118828}},{"type":"Feature","geometry":{"type":"Polygon","coordinates":[[[18.2158,48.1259],[18.2149,48.1252],[18.2124,48.1263],[18.2158,48.1259]]]},"properties":{"Kateg\u00f3ria lesa":"H","V\u00fdmera v m2":22051.0,"OBJECTID":1118850}},{"type":"Feature","geometry":{"type":"Polygon","coordinates":[[[18.21,48.1127],[18.2137,48.1132],[18.2145,48.1103],[18.21,48.1127]]]},"properties":{"Kateg\u00f3ria lesa":"H","V\u00fdmera v m2":47900.0,"OBJECTID":1118939}},{"type":"Feature","geometry":{"type":"Polygon","coordinates":[[[18.2171,48.1486],[18.2162,48.1475],[18.2139,48.1493],[18.2171,48.1486]]]},"properties":{"Kateg\u00f3ria lesa":"H","V\u00fdmera v m2":30750.0,"OBJECTID":1118943}},{"type":"Feature","geometry":{"type":"Polygon","coordinates":[[[18.2191,48.1249],[18.2176,48.1242],[18.2174,48.125],[18.2191,48.1249]]]},"properties":{"Kateg\u00f3ria lesa":"H","V\u00fdmera v m2":10456.0,"OBJECTID":1119263}},{"type":"Feature","geometry":{"type":"Polygon","coordinates":[[[18.2171,48.1131],[18.2139,48.1125],[18.2138,48.1132],[18.2171,48.1131]]]},"properties":{"Kateg\u00f3ria lesa":"H","V\u00fdmera v m2":13706.0,"OBJECTID":1119356}},{"type":"Feature","geometry":{"type":"Polygon","coordinates":[[[18.2176,48.1547],[18.2166,48.155],[18.2173,48.1552],[18.2176,48.1547]]]},"properties":{"Kateg\u00f3ria lesa":"H","V\u00fdmera v m2":2656.0,"OBJECTID":1119381}},{"type":"Feature","geometry":{"type":"Polygon","coordinates":[[[18.2155,48.1174],[18.2173,48.1163],[18.2146,48.1157],[18.2155,48.1174]]]},"properties":{"Kateg\u00f3ria lesa":"H","V\u00fdmera v m2":30713.0,"OBJECTID":1119494}},{"type":"Feature","geometry":{"type":"Polygon","coordinates":[[[18.2082,48.122],[18.2087,48.1202],[18.2065,48.12],[18.2082,48.122]]]},"properties":{"Kateg\u00f3ria lesa":"H","V\u00fdmera v m2":20971.0,"OBJECTID":1119517}},{"type":"Feature","geometry":{"type":"Polygon","coordinates":[[[18.219,48.1526],[18.2176,48.154],[18.2186,48.1542],[18.219,48.1526]]]},"properties":{"Kateg\u00f3ria lesa":"H","V\u00fdmera v m2":12536.0,"OBJECTID":1119806}},{"type":"Feature","geometry":{"type":"Polygon","coordinates":[[[18.2149,48.1196],[18.2145,48.1209],[18.2164,48.1211],[18.2149,48.1196]]]},"properties":{"Kateg\u00f3ria lesa":"H","V\u00fdmera v m2":11059.0,"OBJECTID":1119819}},{"type":"Feature","geometry":{"type":"Polygon","coordinates":[[[18.2108,48.113],[18.2073,48.1146],[18.2102,48.115],[18.2108,48.113]],[[18.2108,48.113],[18.2108,48.1128],[18.2106,48.1129],[18.2108,48.113]]]},"properties":{"Kateg\u00f3ria lesa":"H","V\u00fdmera v m2":26437.0,"OBJECTID":1119828}},{"type":"Feature","geometry":{"type":"Polygon","coordinates":[[[18.2117,48.1152],[18.2109,48.1177],[18.2124,48.1179],[18.2117,48.1152]]]},"properties":{"Kateg\u00f3ria lesa":"H","V\u00fdmera v m2":31311.0,"OBJECTID":1119928}},{"type":"Feature","geometry":{"type":"Polygon","coordinates":[[[18.2165,48.1135],[18.2137,48.1132],[18.2131,48.1153],[18.2165,48.1135]]]},"properties":{"Kateg\u00f3ria lesa":"H","V\u00fdmera v m2":38978.0,"OBJECTID":1120078}},{"type":"Feature","geometry":{"type":"Polygon","coordinates":[[[18.2157,48.152],[18.2118,48.151],[18.2112,48.1516],[18.2157,48.152]]]},"properties":{"Kateg\u00f3ria lesa":"H","V\u00fdmera v m2":17984.0,"OBJECTID":1120123}},{"type":"Feature","geometry":{"type":"Polygon","coordinates":[[[18.2132,48.1273],[18.2109,48.1277],[18.2135,48.1277],[18.2132,48.1273]]]},"properties":{"Kateg\u00f3ria lesa":"H","V\u00fdmera v m2":7038.0,"OBJECTID":1120259}},{"type":"Feature","geometry":{"type":"Polygon","coordinates":[[[18.2144,48.1602],[18.2135,48.1622],[18.2143,48.1623],[18.2144,48.1602]]]},"properties":{"Kateg\u00f3ria lesa":"H","V\u00fdmera v m2":12692.0,"OBJECTID":1120362}},{"type":"Feature","geometry":{"type":"Polygon","coordinates":[[[18.2179,48.1194],[18.2149,48.1194],[18.2175,48.1212],[18.2179,48.1194]]]},"properties":{"Kateg\u00f3ria lesa":"H","V\u00fdmera v m2":13283.0,"OBJECTID":1120390}},{"type":"Feature","geometry":{"type":"Polygon","coordinates":[[[18.2013,48.155],[18.2013,48.1551],[18.2039,48.1552],[18.2013,48.155]]]},"properties":{"Kateg\u00f3ria lesa":"H","V\u00fdmera v m2":3738.0,"OBJECTID":1120631}},{"type":"Feature","geometry":{"type":"Polygon","coordinates":[[[18.2182,48.1513],[18.2174,48.1499],[18.2168,48.1513],[18.2182,48.1513]]]},"properties":{"Kateg\u00f3ria lesa":"H","V\u00fdmera v m2":16169.0,"OBJECTID":1120641}},{"type":"Feature","geometry":{"type":"Polygon","coordinates":[[[18.2191,48.1501],[18.2182,48.1513],[18.2186,48.1514],[18.2191,48.1501]]]},"properties":{"Kateg\u00f3ria lesa":"H","V\u00fdmera v m2":4127.0,"OBJECTID":1120679}},{"type":"Feature","geometry":{"type":"Polygon","coordinates":[[[18.2174,48.1212],[18.2145,48.1209],[18.2141,48.1224],[18.2174,48.1212]]]},"properties":{"Kateg\u00f3ria lesa":"H","V\u00fdmera v m2":38102.0,"OBJECTID":1120721}},{"type":"Feature","geometry":{"type":"Polygon","coordinates":[[[18.2138,48.1181],[18.213,48.1207],[18.2145,48.1208],[18.2138,48.1181]]]},"properties":{"Kateg\u00f3ria lesa":"H","V\u00fdmera v m2":30569.0,"OBJECTID":1120904}},{"type":"Feature","geometry":{"type":"Polygon","coordinates":[[[18.2156,48.1645],[18.2161,48.1628],[18.214,48.1623],[18.2156,48.1645]]]},"properties":{"Kateg\u00f3ria lesa":"H","V\u00fdmera v m2":15921.0,"OBJECTID":1120914}},{"type":"Feature","geometry":{"type":"Polygon","coordinates":[[[18.2172,48.1587],[18.2139,48.159],[18.2168,48.1608],[18.2172,48.1587]]]},"properties":{"Kateg\u00f3ria lesa":"H","V\u00fdmera v m2":40979.0,"OBJECTID":1120986}},{"type":"Feature","geometry":{"type":"Polygon","coordinates":[[[18.2272,48.163],[18.2263,48.1616],[18.2234,48.1608],[18.2272,48.163]]]},"properties":{"Kateg\u00f3ria lesa":"H","V\u00fdmera v m2":22841.0,"OBJECTID":1120999}},{"type":"Feature","geometry":{"type":"Polygon","coordinates":[[[18.2111,48.1191],[18.2087,48.1202],[18.2116,48.1205],[18.2111,48.1191]],[[18.2112,48.1178],[18.2095,48.1175],[18.2093,48.1182],[18.2112,48.1178]]]},"properties":{"Kateg\u00f3ria lesa":"H","V\u00fdmera v m2":39734.0,"OBJECTID":1121184}},{"type":"Feature","geometry":{"type":"Polygon","coordinates":[[[18.2183,48.159],[18.219,48.1566],[18.2168,48.1608],[18.2183,48.159]],[[18.214,48.159],[18.2138,48.16],[18.2144,48.1602],[18.214,48.159]]]},"properties":{"Kateg\u00f3ria lesa":"H","V\u00fdmera v m2":27301.0,"OBJECTID":1121384}},{"type":"Feature","geometry":{"type":"Polygon","coordinates":[[[18.2117,48.1152],[18.2102,48.115],[18.2095,48.1175],[18.2117,48.1152]]]},"properties":{"Kateg\u00f3ria lesa":"H","V\u00fdmera v m2":30069.0,"OBJECTID":1121410}},{"type":"Feature","geometry":{"type":"Polygon","coordinates":[[[18.2198,48.1484],[18.218,48.1499],[18.2191,48.1501],[18.2198,48.1484]]]},"properties":{"Kateg\u00f3ria lesa":"H","V\u00fdmera v m2":16575.0,"OBJECTID":1121447}},{"type":"Feature","geometry":{"type":"Polygon","coordinates":[[[18.2198,48.1484],[18.2182,48.1524],[18.2209,48.1495],[18.2208,48.1528],[18.2198,48.1484]],[[18.2208,48.152],[18.2201,48.1508],[18.2213,48.1497],[18.2208,48.152]]]},"properties":{"Kateg\u00f3ria lesa":"H","V\u00fdmera v m2":39299.0,"OBJECTID":1121460}},{"type":"Feature","geometry":{"type":"Polygon","coordinates":[[[18.2138,48.1234],[18.2108,48.1236],[18.2136,48.124],[18.2138,48.1234]]]},"properties":{"Kateg\u00f3ria lesa":"H","V\u00fdmera v m2":14781.0,"OBJECTID":1121475}},{"type":"Feature","geometry":{"type":"Polygon","coordinates":[[[18.2116,48.1205],[18.2082,48.122],[18.2111,48.1222],[18.2116,48.1205]]]},"properties":{"Kateg\u00f3ria lesa":"H","V\u00fdmera v m2":30924.0,"OBJECTID":1121702}},{"type":"Feature","geometry":{"type":"Polygon","coordinates":[[[18.2139,48.1257],[18.2121,48.1243],[18.2135,48.1259],[18.2139,48.1257]]]},"properties":{"Kateg\u00f3ria lesa":"H","V\u00fdmera v m2":8062.0,"OBJECTID":1121773}},{"type":"Feature","geometry":{"type":"Polygon","coordinates":[[[18.2159,48.1512],[18.215,48.1494],[18.2147,48.1518],[18.2159,48.1512]]]},"properties":{"Kateg\u00f3ria lesa":"H","V\u00fdmera v m2":22980.0,"OBJECTID":1121782}},{"type":"Feature","geometry":{"type":"Polygon","coordinates":[[[18.2153,48.1527],[18.2113,48.1518],[18.2115,48.1527],[18.2153,48.1527]]]},"properties":{"Kateg\u00f3ria lesa":"H","V\u00fdmera v m2":21989.0,"OBJECTID":1121874}},{"type":"Feature","geometry":{"type":"Polygon","coordinates":[[[18.2272,48.1634],[18.2262,48.1633],[18.227,48.1643],[18.2272,48.1634]]]},"properties":{"Kateg\u00f3ria lesa":"H","V\u00fdmera v m2":3828.0,"OBJECTID":1121921}},{"type":"Feature","geometry":{"type":"Polygon","coordinates":[[[18.2149,48.1194],[18.2169,48.1211],[18.2173,48.1198],[18.2149,48.1194]]]},"properties":{"Kateg\u00f3ria lesa":"H","V\u00fdmera v m2":18124.0,"OBJECTID":1121953}},{"type":"Feature","geometry":{"type":"Polygon","coordinates":[[[18.2143,48.1256],[18.2128,48.1244],[18.2139,48.1257],[18.2143,48.1256]]]},"properties":{"Kateg\u00f3ria lesa":"H","V\u00fdmera v m2":4954.0,"OBJECTID":1122035}},{"type":"Feature","geometry":{"type":"Polygon","coordinates":[[[18.2208,48.1528],[18.2196,48.1506],[18.219,48.1526],[18.2208,48.1528]]]},"properties":{"Kateg\u00f3ria lesa":"H","V\u00fdmera v m2":11818.0,"OBJECTID":1122240}},{"type":"Feature","geometry":{"type":"Polygon","coordinates":[[[18.2091,48.119],[18.2066,48.1172],[18.2062,48.1193],[18.2091,48.119]]]},"properties":{"Kateg\u00f3ria lesa":"H","V\u00fdmera v m2":49404.0,"OBJECTID":1122408}},{"type":"Feature","geometry":{"type":"Polygon","coordinates":[[[18.2232,48.1646],[18.2256,48.1653],[18.2235,48.1622],[18.2232,48.1646]]]},"properties":{"Kateg\u00f3ria lesa":"H","V\u00fdmera v m2":41643.0,"OBJECTID":1122415}},{"type":"Feature","geometry":{"type":"Polygon","coordinates":[[[18.2197,48.1116],[18.2168,48.1096],[18.2144,48.1111],[18.2197,48.1116]]]},"properties":{"Kateg\u00f3ria lesa":"H","V\u00fdmera v m2":60432.0,"OBJECTID":1122499}},{"type":"Feature","geometry":{"type":"Polygon","coordinates":[[[18.2341,48.1377],[18.2349,48.1358],[18.2322,48.1351],[18.2341,48.1377]]]},"properties":{"Kateg\u00f3ria lesa":"H","V\u00fdmera v m2":30049.0,"OBJECTID":1122571}},{"type":"Feature","geometry":{"type":"Polygon","coordinates":[[[18.2138,48.1181],[18.2124,48.1179],[18.2117,48.1205],[18.2138,48.1181]]]},"properties":{"Kateg\u00f3ria lesa":"H","V\u00fdmera v m2":31385.0,"OBJECTID":1122575}},{"type":"Feature","geometry":{"type":"Polygon","coordinates":[[[18.2167,48.124],[18.217,48.1228],[18.2141,48.1225],[18.2167,48.124]]]},"properties":{"Kateg\u00f3ria lesa":"H","V\u00fdmera v m2":25033.0,"OBJECTID":1122707}},{"type":"Feature","geometry":{"type":"Polygon","coordinates":[[[18.2198,48.1585],[18.2189,48.1571],[18.2184,48.1588],[18.2198,48.1585]]]},"properties":{"Kateg\u00f3ria lesa":"H","V\u00fdmera v m2":12454.0,"OBJECTID":1122714}},{"type":"Feature","geometry":{"type":"Polygon","coordinates":[[[18.2341,48.1256],[18.232,48.1246],[18.233,48.1261],[18.2341,48.1256]],[[18.231,48.127],[18.231,48.1261],[18.2298,48.126],[18.231,48.127]]]},"properties":{"Kateg\u00f3ria lesa":"H","V\u00fdmera v m2":25523.0,"OBJECTID":1122779}},{"type":"Feature","geometry":{"type":"Polygon","coordinates":[[[18.2112,48.1178],[18.2091,48.119],[18.212,48.1192],[18.2112,48.1178]]]},"properties":{"Kateg\u00f3ria lesa":"H","V\u00fdmera v m2":24423.0,"OBJECTID":1122791}},{"type":"Feature","geometry":{"type":"Polygon","coordinates":[[[18.2159,48.1258],[18.2167,48.124],[18.2139,48.1232],[18.2159,48.1258]]]},"properties":{"Kateg\u00f3ria lesa":"H","V\u00fdmera v m2":37365.0,"OBJECTID":1122839}},{"type":"Feature","geometry":{"type":"Polygon","coordinates":[[[18.2133,48.1244],[18.2136,48.124],[18.2107,48.1241],[18.2133,48.1244]]]},"properties":{"Kateg\u00f3ria lesa":"H","V\u00fdmera v m2":10989.0,"OBJECTID":1122849}},{"type":"Feature","geometry":{"type":"Polygon","coordinates":[[[18.2087,48.116],[18.207,48.1158],[18.2067,48.1171],[18.2087,48.116]],[[18.2094,48.116],[18.2087,48.1174],[18.2095,48.1175],[18.2094,48.116]]]},"properties":{"Kateg\u00f3ria lesa":"H","V\u00fdmera v m2":26743.0,"OBJECTID":1122957}},{"type":"Feature","geometry":{"type":"Polygon","coordinates":[[[18.2148,48.1545],[18.2111,48.1529],[18.2132,48.1559],[18.2148,48.1545]]]},"properties":{"Kateg\u00f3ria lesa":"H","V\u00fdmera v m2":49580.0,"OBJECTID":1123009}},{"type":"Feature","geometry":{"type":"Polygon","coordinates":[[[18.2108,48.1255],[18.2106,48.1241],[18.2079,48.122],[18.2108,48.1255]],[[18.2078,48.1221],[18.2072,48.122],[18.2073,48.1223],[18.2078,48.1221]],[[18.211,48.1258],[18.2109,48.1256],[18.2103,48.1256],[18.211,48.1258]]]},"properties":{"Kateg\u00f3ria lesa":"H","V\u00fdmera v m2":17855.0,"OBJECTID":1123014}},{"type":"Feature","geometry":{"type":"Polygon","coordinates":[[[18.2101,48.1251],[18.2085,48.1237],[18.2092,48.1253],[18.2101,48.1251]]]},"properties":{"Kateg\u00f3ria lesa":"H","V\u00fdmera v m2":8725.0,"OBJECTID":1123100}},{"type":"Feature","geometry":{"type":"Polygon","coordinates":[[[18.1969,48.1492],[18.1946,48.1496],[18.1987,48.1496],[18.1969,48.1492]]]},"properties":{"Kateg\u00f3ria lesa":"H","V\u00fdmera v m2":36196.0,"OBJECTID":1123325}},{"type":"Feature","geometry":{"type":"Polygon","coordinates":[[[18.2145,48.1209],[18.2117,48.1206],[18.2112,48.1222],[18.2145,48.1209]]]},"properties":{"Kateg\u00f3ria lesa":"H","V\u00fdmera v m2":38469.0,"OBJECTID":1123358}},{"type":"Feature","geometry":{"type":"Polygon","coordinates":[[[18.2234,48.1622],[18.2178,48.161],[18.2172,48.1632],[18.2227,48.1645],[18.2234,48.1622]]]},"properties":{"Kateg\u00f3ria lesa":"H","V\u00fdmera v m2":89853.0,"OBJECTID":1123455}},{"type":"Feature","geometry":{"type":"Polygon","coordinates":[[[18.2139,48.1232],[18.2112,48.1222],[18.211,48.123],[18.2139,48.1232]]]},"properties":{"Kateg\u00f3ria lesa":"H","V\u00fdmera v m2":21492.0,"OBJECTID":1123463}},{"type":"Feature","geometry":{"type":"Polygon","coordinates":[[[18.2186,48.1514],[18.2164,48.1497],[18.2159,48.1512],[18.2186,48.1514]]]},"properties":{"Kateg\u00f3ria lesa":"H","V\u00fdmera v m2":21200.0,"OBJECTID":1123496}},{"type":"Feature","geometry":{"type":"Polygon","coordinates":[[[18.2109,48.1277],[18.2132,48.1273],[18.2105,48.1268],[18.2109,48.1277]]]},"properties":{"Kateg\u00f3ria lesa":"H","V\u00fdmera v m2":11718.0,"OBJECTID":1123532}},{"type":"Feature","geometry":{"type":"Polygon","coordinates":[[[18.2148,48.1505],[18.2131,48.1515],[18.2147,48.1518],[18.2148,48.1505]]]},"properties":{"Kateg\u00f3ria lesa":"H","V\u00fdmera v m2":11152.0,"OBJECTID":1123538}},{"type":"Feature","geometry":{"type":"Polygon","coordinates":[[[18.1947,48.1233],[18.1934,48.122],[18.1923,48.1231],[18.1947,48.1233]],[[18.1935,48.1232],[18.1921,48.1235],[18.1934,48.1237],[18.1935,48.1232]],[[18.1953,48.1223],[18.1927,48.122],[18.1939,48.1238],[18.1953,48.1223]]]},"properties":{"Kateg\u00f3ria lesa":"H","V\u00fdmera v m2":29116.0,"OBJECTID":1123688}},{"type":"Feature","geometry":{"type":"Polygon","coordinates":[[[18.2144,48.1111],[18.2154,48.1119],[18.2156,48.111],[18.2144,48.1111]]]},"properties":{"Kateg\u00f3ria lesa":"H","V\u00fdmera v m2":7752.0,"OBJECTID":1123754}},{"type":"Feature","geometry":{"type":"Polygon","coordinates":[[[18.2155,48.1524],[18.2132,48.1521],[18.2153,48.1527],[18.2155,48.1524]]]},"properties":{"Kateg\u00f3ria lesa":"H","V\u00fdmera v m2":7230.0,"OBJECTID":1123894}},{"type":"Feature","geometry":{"type":"Polygon","coordinates":[[[18.2135,48.1259],[18.2107,48.1241],[18.2124,48.1263],[18.2135,48.1259]]]},"properties":{"Kateg\u00f3ria lesa":"H","V\u00fdmera v m2":22195.0,"OBJECTID":1123982}},{"type":"Feature","geometry":{"type":"Polygon","coordinates":[[[18.1934,48.1237],[18.1916,48.1248],[18.1935,48.1251],[18.1934,48.1237]]]},"properties":{"Kateg\u00f3ria lesa":"H","V\u00fdmera v m2":19105.0,"OBJECTID":1124024}},{"type":"Feature","geometry":{"type":"Polygon","coordinates":[[[18.2155,48.1645],[18.2135,48.1622],[18.2125,48.1639],[18.2155,48.1645]]]},"properties":{"Kateg\u00f3ria lesa":"H","V\u00fdmera v m2":31619.0,"OBJECTID":1124056}},{"type":"Feature","geometry":{"type":"Polygon","coordinates":[[[18.2185,48.1166],[18.2152,48.1182],[18.2182,48.1186],[18.2185,48.1166]]]},"properties":{"Kateg\u00f3ria lesa":"H","V\u00fdmera v m2":40961.0,"OBJECTID":1124124}},{"type":"Feature","geometry":{"type":"Polygon","coordinates":[[[18.207,48.1157],[18.2045,48.1144],[18.2038,48.1168],[18.207,48.1157]]]},"properties":{"Kateg\u00f3ria lesa":"H","V\u00fdmera v m2":47224.0,"OBJECTID":1124191}},{"type":"Feature","geometry":{"type":"Polygon","coordinates":[[[18.2092,48.1159],[18.2082,48.1173],[18.2089,48.1172],[18.2092,48.1159]]]},"properties":{"Kateg\u00f3ria lesa":"H","V\u00fdmera v m2":7516.0,"OBJECTID":1124193}},{"type":"Feature","geometry":{"type":"Polygon","coordinates":[[[18.2152,48.1531],[18.2114,48.1528],[18.215,48.1535],[18.2152,48.1531]]]},"properties":{"Kateg\u00f3ria lesa":"H","V\u00fdmera v m2":6322.0,"OBJECTID":1124253}},{"type":"Feature","geometry":{"type":"Polygon","coordinates":[[[18.2201,48.1115],[18.2196,48.1104],[18.2168,48.1096],[18.2201,48.1115]]]},"properties":{"Kateg\u00f3ria lesa":"H","V\u00fdmera v m2":25894.0,"OBJECTID":1124549}},{"type":"Feature","geometry":{"type":"Polygon","coordinates":[[[18.2137,48.1132],[18.2102,48.115],[18.213,48.1153],[18.2137,48.1132]],[[18.212,48.1129],[18.2108,48.1128],[18.2137,48.1132],[18.212,48.1129]]]},"properties":{"Kateg\u00f3ria lesa":"H","V\u00fdmera v m2":51740.0,"OBJECTID":1124659}},{"type":"Feature","geometry":{"type":"Polygon","coordinates":[[[18.2078,48.1133],[18.2095,48.1127],[18.2056,48.1133],[18.2078,48.1133]]]},"properties":{"Kateg\u00f3ria lesa":"H","V\u00fdmera v m2":8315.0,"OBJECTID":1124748}},{"type":"Feature","geometry":{"type":"Polygon","coordinates":[[[18.2077,48.1135],[18.2063,48.1135],[18.2066,48.1145],[18.2077,48.1135]],[[18.2075,48.1142],[18.2068,48.1145],[18.2073,48.1146],[18.2075,48.1142]]]},"properties":{"Kateg\u00f3ria lesa":"H","V\u00fdmera v m2":10027.0,"OBJECTID":1124803}},{"type":"Feature","geometry":{"type":"Polygon","coordinates":[[[18.2206,48.1537],[18.219,48.1526],[18.2186,48.1542],[18.2206,48.1537]]]},"properties":{"Kateg\u00f3ria lesa":"H","V\u00fdmera v m2":20434.0,"OBJECTID":1124900}},{"type":"Feature","geometry":{"type":"Polygon","coordinates":[[[18.2111,48.1222],[18.2086,48.122],[18.2088,48.1236],[18.2111,48.1222]]]},"properties":{"Kateg\u00f3ria lesa":"H","V\u00fdmera v m2":34156.0,"OBJECTID":1124923}},{"type":"Feature","geometry":{"type":"Polygon","coordinates":[[[18.2172,48.1267],[18.2188,48.1252],[18.2158,48.1259],[18.2172,48.1267]],[[18.2195,48.1245],[18.2188,48.1246],[18.2191,48.1249],[18.2195,48.1245]]]},"properties":{"Kateg\u00f3ria lesa":"H","V\u00fdmera v m2":15272.0,"OBJECTID":1124947}},{"type":"Feature","geometry":{"type":"Polygon","coordinates":[[[18.2322,48.1249],[18.2301,48.1258],[18.233,48.1261],[18.2322,48.1249]],[[18.235,48.1239],[18.2327,48.1243],[18.2341,48.1256],[18.235,48.1239]],[[18.2288,48.1275],[18.2308,48.1269],[18.2298,48.126],[18.2288,48.1275]]]},"properties":{"Kateg\u00f3ria lesa":"H","V\u00fdmera v m2":56310.0,"OBJECTID":1124984}},{"type":"Feature","geometry":{"type":"Polygon","coordinates":[[[18.2174,48.125],[18.2159,48.1258],[18.2172,48.1265],[18.2174,48.125]]]},"properties":{"Kateg\u00f3ria lesa":"H","V\u00fdmera v m2":18456.0,"OBJECTID":1125216}},{"type":"Feature","geometry":{"type":"Polygon","coordinates":[[[18.2184,48.152],[18.2159,48.1512],[18.2157,48.152],[18.2184,48.152]]]},"properties":{"Kateg\u00f3ria lesa":"H","V\u00fdmera v m2":10860.0,"OBJECTID":1125283}},{"type":"Feature","geometry":{"type":"Polygon","coordinates":[[[18.2333,48.1384],[18.2318,48.1376],[18.2315,48.1389],[18.2333,48.1384]]]},"properties":{"Kateg\u00f3ria lesa":"H","V\u00fdmera v m2":12913.0,"OBJECTID":1125329}},{"type":"Feature","geometry":{"type":"Polygon","coordinates":[[[18.207,48.1158],[18.2054,48.1162],[18.2067,48.1171],[18.207,48.1158]]]},"properties":{"Kateg\u00f3ria lesa":"H","V\u00fdmera v m2":11723.0,"OBJECTID":1125338}},{"type":"Feature","geometry":{"type":"Polygon","coordinates":[[[18.2346,48.1477],[18.2334,48.1484],[18.2345,48.1488],[18.2346,48.1477]]]},"properties":{"Kateg\u00f3ria lesa":"H","V\u00fdmera v m2":10309.0,"OBJECTID":1125436}},{"type":"Feature","geometry":{"type":"Polygon","coordinates":[[[18.2182,48.1524],[18.215,48.1535],[18.2176,48.154],[18.2182,48.1524]]]},"properties":{"Kateg\u00f3ria lesa":"H","V\u00fdmera v m2":35941.0,"OBJECTID":1125439}},{"type":"Feature","geometry":{"type":"Polygon","coordinates":[[[18.2062,48.1193],[18.2067,48.1214],[18.2079,48.122],[18.2062,48.1193]],[[18.2076,48.122],[18.207,48.1217],[18.2072,48.122],[18.2076,48.122]]]},"properties":{"Kateg\u00f3ria lesa":"H","V\u00fdmera v m2":9208.0,"OBJECTID":1125477}},{"type":"Feature","geometry":{"type":"Polygon","coordinates":[[[18.2192,48.156],[18.2176,48.154],[18.2167,48.1563],[18.2192,48.156]]]},"properties":{"Kateg\u00f3ria lesa":"H","V\u00fdmera v m2":38963.0,"OBJECTID":1125521}},{"type":"Feature","geometry":{"type":"Polygon","coordinates":[[[18.2149,48.1252],[18.2133,48.1244],[18.2143,48.1256],[18.2149,48.1252]]]},"properties":{"Kateg\u00f3ria lesa":"H","V\u00fdmera v m2":7456.0,"OBJECTID":1125630}},{"type":"Feature","geometry":{"type":"Polygon","coordinates":[[[18.2165,48.1607],[18.2144,48.1602],[18.2143,48.1623],[18.2165,48.1607]]]},"properties":{"Kateg\u00f3ria lesa":"H","V\u00fdmera v m2":30892.0,"OBJECTID":1125688}},{"type":"Feature","geometry":{"type":"Polygon","coordinates":[[[18.2104,48.1127],[18.2078,48.1133],[18.2075,48.1141],[18.2104,48.1127]],[[18.2101,48.1132],[18.2074,48.1144],[18.2083,48.1142],[18.2101,48.1132]]]},"properties":{"Kateg\u00f3ria lesa":"H","V\u00fdmera v m2":18820.0,"OBJECTID":1125698}},{"type":"Feature","geometry":{"type":"Polygon","coordinates":[[[18.2171,48.1486],[18.2177,48.1473],[18.2163,48.1484],[18.2171,48.1486]]]},"properties":{"Kateg\u00f3ria lesa":"H","V\u00fdmera v m2":7138.0,"OBJECTID":1125759}},{"type":"Feature","geometry":{"type":"Polygon","coordinates":[[[18.2182,48.1594],[18.2178,48.161],[18.2203,48.1608],[18.2182,48.1594]]]},"properties":{"Kateg\u00f3ria lesa":"H","V\u00fdmera v m2":19283.0,"OBJECTID":1125883}},{"type":"Feature","geometry":{"type":"Polygon","coordinates":[[[18.2102,48.115],[18.207,48.1158],[18.2099,48.1162],[18.2102,48.115]]]},"properties":{"Kateg\u00f3ria lesa":"H","V\u00fdmera v m2":27262.0,"OBJECTID":1125897}},{"type":"Feature","geometry":{"type":"Polygon","coordinates":[[[18.2066,48.114],[18.2052,48.1136],[18.2047,48.1143],[18.2066,48.114]]]},"properties":{"Kateg\u00f3ria lesa":"H","V\u00fdmera v m2":8844.0,"OBJECTID":1125947}},{"type":"Feature","geometry":{"type":"Polygon","coordinates":[[[18.2062,48.1136],[18.2052,48.1136],[18.2066,48.114],[18.2062,48.1136]]]},"properties":{"Kateg\u00f3ria lesa":"H","V\u00fdmera v m2":3839.0,"OBJECTID":1125998}},{"type":"Feature","geometry":{"type":"Polygon","coordinates":[[[18.2013,48.155],[18.1999,48.155],[18.2013,48.1551],[18.2013,48.155]]]},"properties":{"Kateg\u00f3ria lesa":"H","V\u00fdmera v m2":2110.0,"OBJECTID":1126023}},{"type":"Feature","geometry":{"type":"Polygon","coordinates":[[[18.2169,48.1643],[18.2161,48.1628],[18.2156,48.1645],[18.2169,48.1643]]]},"properties":{"Kateg\u00f3ria lesa":"H","V\u00fdmera v m2":13870.0,"OBJECTID":1126108}},{"type":"Feature","geometry":{"type":"Polygon","coordinates":[[[18.2148,48.1505],[18.2139,48.1493],[18.2118,48.151],[18.2148,48.1505]]]},"properties":{"Kateg\u00f3ria lesa":"H","V\u00fdmera v m2":24635.0,"OBJECTID":1126127}},{"type":"Feature","geometry":{"type":"Polygon","coordinates":[[[18.2587,48.1161],[18.2573,48.1151],[18.2581,48.1166],[18.2587,48.1161]]]},"properties":{"Kateg\u00f3ria lesa":"H","V\u00fdmera v m2":5632.0,"OBJECTID":1126226}},{"type":"Feature","geometry":{"type":"Polygon","coordinates":[[[18.2675,48.1187],[18.2668,48.1186],[18.2672,48.1189],[18.2675,48.1187]],[[18.2674,48.1181],[18.2673,48.1182],[18.2674,48.1184],[18.2674,48.1181]]]},"properties":{"Kateg\u00f3ria lesa":"H","V\u00fdmera v m2":1513.0,"OBJECTID":1127155}},{"type":"Feature","geometry":{"type":"Polygon","coordinates":[[[18.2615,48.1152],[18.2613,48.1128],[18.2591,48.1139],[18.2615,48.1152]]]},"properties":{"Kateg\u00f3ria lesa":"H","V\u00fdmera v m2":43771.0,"OBJECTID":1127456}},{"type":"Feature","geometry":{"type":"Polygon","coordinates":[[[18.2614,48.1123],[18.2579,48.1121],[18.2578,48.1136],[18.2614,48.1123]]]},"properties":{"Kateg\u00f3ria lesa":"H","V\u00fdmera v m2":34381.0,"OBJECTID":1127872}},{"type":"Feature","geometry":{"type":"Polygon","coordinates":[[[18.2546,48.1115],[18.2535,48.1123],[18.2556,48.113],[18.2546,48.1115]]]},"properties":{"Kateg\u00f3ria lesa":"H","V\u00fdmera v m2":11468.0,"OBJECTID":1127901}},{"type":"Feature","geometry":{"type":"Polygon","coordinates":[[[18.2622,48.1088],[18.261,48.1102],[18.2618,48.1102],[18.2622,48.1088]]]},"properties":{"Kateg\u00f3ria lesa":"H","V\u00fdmera v m2":5600.0,"OBJECTID":1128712}},{"type":"Feature","geometry":{"type":"Polygon","coordinates":[[[18.2663,48.1159],[18.2645,48.1155],[18.2669,48.1185],[18.2663,48.1159]],[[18.2644,48.1156],[18.2642,48.1157],[18.2657,48.1171],[18.2644,48.1156]],[[18.2684,48.1182],[18.2675,48.1173],[18.2675,48.1197],[18.2684,48.1182]]]},"properties":{"Kateg\u00f3ria lesa":"H","V\u00fdmera v m2":56433.0,"OBJECTID":1129508}},{"type":"Feature","geometry":{"type":"Polygon","coordinates":[[[18.2613,48.1102],[18.2619,48.1082],[18.2599,48.1108],[18.2613,48.1102]]]},"properties":{"Kateg\u00f3ria lesa":"H","V\u00fdmera v m2":27200.0,"OBJECTID":1131409}},{"type":"Feature","geometry":{"type":"Polygon","coordinates":[[[18.2675,48.1197],[18.2642,48.1157],[18.2629,48.1165],[18.2675,48.1197]]]},"properties":{"Kateg\u00f3ria lesa":"H","V\u00fdmera v m2":57874.0,"OBJECTID":1131482}},{"type":"Feature","geometry":{"type":"Polygon","coordinates":[[[18.2604,48.1088],[18.2579,48.1092],[18.2599,48.1108],[18.2604,48.1088]]]},"properties":{"Kateg\u00f3ria lesa":"H","V\u00fdmera v m2":29735.0,"OBJECTID":1131589}},{"type":"Feature","geometry":{"type":"Polygon","coordinates":[[[18.2599,48.1153],[18.2589,48.1138],[18.2567,48.1147],[18.2599,48.1153]]]},"properties":{"Kateg\u00f3ria lesa":"H","V\u00fdmera v m2":37200.0,"OBJECTID":1132106}},{"type":"Feature","geometry":{"type":"Polygon","coordinates":[[[18.2776,48.1531],[18.2763,48.1528],[18.2768,48.154],[18.2776,48.1531]]]},"properties":{"Kateg\u00f3ria lesa":"H","V\u00fdmera v m2":10836.0,"OBJECTID":1132355}},{"type":"Feature","geometry":{"type":"Polygon","coordinates":[[[18.2577,48.1137],[18.2577,48.1119],[18.2546,48.1115],[18.2577,48.1137]]]},"properties":{"Kateg\u00f3ria lesa":"H","V\u00fdmera v m2":45133.0,"OBJECTID":1132727}},{"type":"Feature","geometry":{"type":"Polygon","coordinates":[[[18.26,48.1122],[18.2614,48.1122],[18.2574,48.1114],[18.26,48.1122]],[[18.2609,48.1115],[18.2599,48.1114],[18.2615,48.1122],[18.2609,48.1115]]]},"properties":{"Kateg\u00f3ria lesa":"H","V\u00fdmera v m2":23486.0,"OBJECTID":1135792}},{"type":"Feature","geometry":{"type":"Polygon","coordinates":[[[18.2818,48.1552],[18.281,48.154],[18.2794,48.1546],[18.2818,48.1552]],[[18.2792,48.1545],[18.2806,48.154],[18.2787,48.1541],[18.2792,48.1545]]]},"properties":{"Kateg\u00f3ria lesa":"H","V\u00fdmera v m2":20011.0,"OBJECTID":1136140}},{"type":"Feature","geometry":{"type":"Polygon","coordinates":[[[18.2615,48.1115],[18.2598,48.1108],[18.2598,48.1113],[18.2615,48.1115]]]},"properties":{"Kateg\u00f3ria lesa":"H","V\u00fdmera v m2":5744.0,"OBJECTID":1137269}},{"type":"Feature","geometry":{"type":"Polygon","coordinates":[[[18.2582,48.1172],[18.2627,48.1164],[18.2599,48.1153],[18.2582,48.1172]],[[18.2634,48.1168],[18.265,48.1188],[18.2644,48.1176],[18.2634,48.1168]]]},"properties":{"Kateg\u00f3ria lesa":"H","V\u00fdmera v m2":57824.0,"OBJECTID":1138094}},{"type":"Feature","geometry":{"type":"Polygon","coordinates":[[[18.2556,48.113],[18.2529,48.1135],[18.2565,48.1146],[18.2556,48.113]]]},"properties":{"Kateg\u00f3ria lesa":"H","V\u00fdmera v m2":30531.0,"OBJECTID":1138469}},{"type":"Feature","geometry":{"type":"Polygon","coordinates":[[[18.2138,48.1665],[18.2149,48.1652],[18.2129,48.1674],[18.2138,48.1665]],[[18.2124,48.1662],[18.2116,48.1671],[18.2122,48.1672],[18.2124,48.1662]]]},"properties":{"Kateg\u00f3ria lesa":"H","V\u00fdmera v m2":21775.0,"OBJECTID":1166838}},{"type":"Feature","geometry":{"type":"Polygon","coordinates":[[[18.2203,48.1666],[18.2166,48.1656],[18.2156,48.1681],[18.2203,48.1666]]]},"properties":{"Kateg\u00f3ria lesa":"H","V\u00fdmera v m2":35281.0,"OBJECTID":1166981}},{"type":"Feature","geometry":{"type":"Polygon","coordinates":[[[18.2162,48.1668],[18.2149,48.1652],[18.2133,48.1675],[18.2162,48.1668]],[[18.214,48.165],[18.2128,48.1647],[18.2122,48.1672],[18.214,48.165]]]},"properties":{"Kateg\u00f3ria lesa":"H","V\u00fdmera v m2":63897.0,"OBJECTID":1167148}},{"type":"Feature","geometry":{"type":"Polygon","coordinates":[[[18.217,48.1639],[18.217,48.1658],[18.2177,48.164],[18.217,48.1639]]]},"properties":{"Kateg\u00f3ria lesa":"H","V\u00fdmera v m2":7999.0,"OBJECTID":1247314}},{"type":"Feature","geometry":{"type":"Polygon","coordinates":[[[18.2125,48.1659],[18.2119,48.1644],[18.2087,48.1663],[18.2125,48.1659]]]},"properties":{"Kateg\u00f3ria lesa":"H","V\u00fdmera v m2":44607.0,"OBJECTID":1247316}},{"type":"Feature","geometry":{"type":"Polygon","coordinates":[[[18.2169,48.1643],[18.2119,48.1644],[18.2165,48.1656],[18.2169,48.1643]]]},"properties":{"Kateg\u00f3ria lesa":"H","V\u00fdmera v m2":27582.0,"OBJECTID":1247323}},{"type":"Feature","geometry":{"type":"Polygon","coordinates":[[[18.2256,48.1653],[18.2223,48.1672],[18.2246,48.1679],[18.2256,48.1653]]]},"properties":{"Kateg\u00f3ria lesa":"H","V\u00fdmera v m2":45441.0,"OBJECTID":1247326}},{"type":"Feature","geometry":{"type":"Polygon","coordinates":[[[18.2227,48.1645],[18.2191,48.1636],[18.2183,48.1661],[18.2227,48.1645]]]},"properties":{"Kateg\u00f3ria lesa":"H","V\u00fdmera v m2":60494.0,"OBJECTID":1247358}},{"type":"Feature","geometry":{"type":"Polygon","coordinates":[[[18.227,48.1643],[18.226,48.168],[18.2277,48.1665],[18.227,48.1643]]]},"properties":{"Kateg\u00f3ria lesa":"H","V\u00fdmera v m2":33602.0,"OBJECTID":1247360}},{"type":"Feature","geometry":{"type":"Polygon","coordinates":[[[18.2238,48.1648],[18.2206,48.1668],[18.2232,48.1667],[18.2238,48.1648]]]},"properties":{"Kateg\u00f3ria lesa":"H","V\u00fdmera v m2":36891.0,"OBJECTID":1247363}},{"type":"Feature","geometry":{"type":"Polygon","coordinates":[[[18.2191,48.1636],[18.2172,48.1632],[18.217,48.1658],[18.2191,48.1636]]]},"properties":{"Kateg\u00f3ria lesa":"H","V\u00fdmera v m2":31171.0,"OBJECTID":1247368}}]}