{"type":"FeatureCollection","features":[{"type":"Feature","geometry":{"type":"Polygon","coordinates":[[[18.2583,48.3985],[18.2598,48.395],[18.2542,48.3946],[18.2583,48.3985]]]},"properties":{"Popis":"eolick\u00e9 sedimenty: spra\u0161e a jemnopies\u010dit\u00e9 spra\u0161e, v\u00e1pnit\u00e9 a spra\u0161ovit\u00e9 hliny vcelku","\u00datvar":"kvart\u00e9r","Vek1":"pleistoc\u00e9n","S\u00favrstvie":"-","FID":45426}},{"type":"Feature","geometry":{"type":"Polygon","coordinates":[[[18.1903,48.3957],[18.2074,48.3914],[18.1948,48.3869],[18.1803,48.3882],[18.1903,48.3957]]]},"properties":{"Popis":"hrubozrnn\u00e9 biotitick\u00e9 granodiority a\u017e tonality, tektonodeforma\u010dne prepracovan\u00e9","\u00datvar":"kry\u0161talinikum","Vek1":"paleozoikum - herc\u00fdnske granitoidy (karb\u00f3n)","S\u00favrstvie":"-","FID":45581}},{"type":"Feature","geometry":{"type":"Polygon","coordinates":[[[18.2574,48.3998],[18.2542,48.3946],[18.2498,48.3954],[18.2535,48.3917],[18.2418,48.391],[18.2574,48.3998]]]},"properties":{"Popis":"deluvi\u00e1lne sedimenty: preva\u017ene hlinito-kamenit\u00e9 (podradne pies\u010dito-kamenit\u00e9) svahoviny a sutiny","\u00datvar":"kvart\u00e9r","Vek1":"pleistoc\u00e9n - holoc\u00e9n","S\u00favrstvie":"-","FID":45647}},{"type":"Feature","geometry":{"type":"Polygon","coordinates":[[[18.2581,48.4],[18.2672,48.3857],[18.2644,48.3841],[18.2456,48.3925],[18.2633,48.3863],[18.2604,48.3938],[18.2499,48.3951],[18.2596,48.3948],[18.2581,48.4]]]},"properties":{"Popis":"fluvi\u00e1lne sedimenty: litofaci\u00e1lne ne\u010dlenen\u00e9 nivn\u00e9 hliny, alebo pies\u010dit\u00e9 a\u017e \u0161trkovit\u00e9 hliny dolinn\u00fdch n\u00edv a n\u00edv horsk\u00fdch potokov","\u00datvar":"kvart\u00e9r","Vek1":"holoc\u00e9n","S\u00favrstvie":"-","FID":45686}},{"type":"Feature","geometry":{"type":"Polygon","coordinates":[[[18.2929,48.4027],[18.2985,48.4015],[18.2815,48.3937],[18.2776,48.3958],[18.2929,48.4027]]]},"properties":{"Popis":"volkovsk\u00e9 s\u00favrstvie: piesky, \u0161trky, \u00edly, uho\u013en\u00e9 \u00edly","\u00datvar":"neog\u00e9n","Vek1":"plioc\u00e9n","S\u00favrstvie":"volkovsk\u00e9 s\u00favrstvie","FID":45765}},{"type":"Feature","geometry":{"type":"Polygon","coordinates":[[[18.2903,48.4042],[18.2922,48.4025],[18.2839,48.3973],[18.2739,48.3974],[18.2903,48.4042]]]},"properties":{"Popis":"deluvi\u00e1lne sedimenty: preva\u017ene hlinito-kamenit\u00e9 (podradne pies\u010dito-kamenit\u00e9) svahoviny a sutiny","\u00datvar":"kvart\u00e9r","Vek1":"pleistoc\u00e9n - holoc\u00e9n","S\u00favrstvie":"-","FID":46008}},{"type":"Feature","geometry":{"type":"Polygon","coordinates":[[[18.248,48.4019],[18.2478,48.4005],[18.2469,48.4004],[18.248,48.4019]]]},"properties":{"Popis":"dolomity, rauvaky, brekcie, pestr\u00e9 v\u00e1pence, \u017eltkast\u00e9 zrnit\u00e9 dolomity, miestami bune\u010dnat\u00e9 (rauvaky)","\u00datvar":"trias","Vek1":"star\u0161\u00ed - stredn\u00fd trias","S\u00favrstvie":"-","FID":46036}},{"type":"Feature","geometry":{"type":"Polygon","coordinates":[[[18.2293,48.4024],[18.2307,48.3993],[18.2277,48.3984],[18.2293,48.4024]]]},"properties":{"Popis":"trlensk\u00e9 s\u00favrstvie: siv\u00e9 a\u017e tmavosiv\u00e9, pies\u010dito-krinoidov\u00e9 v\u00e1pence so silicitmi, v\u00e1pnit\u00e9 pieskovce s medzivrstvi\u010dkami tmav\u00fdch v\u00e1pnit\u00fdch \u00edlovcov","\u00datvar":"jura","Vek1":"star\u0161ia jura","S\u00favrstvie":"trlensk\u00e9 s\u00favrstvie","FID":46268}},{"type":"Feature","geometry":{"type":"Polygon","coordinates":[[[18.2476,48.4048],[18.2549,48.4002],[18.2475,48.4002],[18.2476,48.4048]]]},"properties":{"Popis":"l\u00fa\u017e\u0148ansk\u00e9 s\u00favrstvie: svetlosiv\u00e9, ru\u017eov\u00e9, \u010derven\u00e9 kremence, kremenn\u00e9 pieskovce, ark\u00f3zov\u00e9 pieskovce, konglomer\u00e1ty","\u00datvar":"trias","Vek1":"star\u0161\u00ed trias","S\u00favrstvie":"l\u00fa\u017e\u0148ansk\u00e9 s\u00favrstvie","FID":46520}},{"type":"Feature","geometry":{"type":"Polygon","coordinates":[[[18.2449,48.4055],[18.2472,48.401],[18.2433,48.4038],[18.2449,48.4055]]]},"properties":{"Popis":"trlensk\u00e9 s\u00favrstvie: siv\u00e9 a\u017e tmavosiv\u00e9, pies\u010dito-krinoidov\u00e9 v\u00e1pence so silicitmi, v\u00e1pnit\u00e9 pieskovce s medzivrstvi\u010dkami tmav\u00fdch v\u00e1pnit\u00fdch \u00edlovcov","\u00datvar":"jura","Vek1":"star\u0161ia jura","S\u00favrstvie":"trlensk\u00e9 s\u00favrstvie","FID":46690}},{"type":"Feature","geometry":{"type":"Polygon","coordinates":[[[18.1985,48.403],[18.2112,48.3937],[18.1971,48.3943],[18.2073,48.3948],[18.2038,48.4011],[18.1985,48.403]]]},"properties":{"Popis":"fluvi\u00e1lne sedimenty: litofaci\u00e1lne ne\u010dlenen\u00e9 nivn\u00e9 hliny, alebo pies\u010dit\u00e9 a\u017e \u0161trkovit\u00e9 hliny dolinn\u00fdch n\u00edv a n\u00edv horsk\u00fdch potokov","\u00datvar":"kvart\u00e9r","Vek1":"holoc\u00e9n","S\u00favrstvie":"-","FID":46701}},{"type":"Feature","geometry":{"type":"Polygon","coordinates":[[[18.2855,48.4082],[18.2913,48.405],[18.2889,48.4051],[18.2855,48.4082]]]},"properties":{"Popis":"fluvi\u00e1lne sedimenty: litofaci\u00e1lne ne\u010dlenen\u00e9 nivn\u00e9 hliny, alebo pies\u010dit\u00e9 a\u017e \u0161trkovit\u00e9 hliny dolinn\u00fdch n\u00edv a n\u00edv horsk\u00fdch potokov","\u00datvar":"kvart\u00e9r","Vek1":"holoc\u00e9n","S\u00favrstvie":"-","FID":46707}},{"type":"Feature","geometry":{"type":"Polygon","coordinates":[[[18.2357,48.4061],[18.2381,48.402],[18.232,48.4043],[18.2357,48.4061]]]},"properties":{"Popis":"trlensk\u00e9 s\u00favrstvie: siv\u00e9 a\u017e tmavosiv\u00e9, pies\u010dito-krinoidov\u00e9 v\u00e1pence so silicitmi, v\u00e1pnit\u00e9 pieskovce s medzivrstvi\u010dkami tmav\u00fdch v\u00e1pnit\u00fdch \u00edlovcov","\u00datvar":"jura","Vek1":"star\u0161ia jura","S\u00favrstvie":"trlensk\u00e9 s\u00favrstvie","FID":46859}},{"type":"Feature","geometry":{"type":"Polygon","coordinates":[[[18.2395,48.4068],[18.2439,48.4058],[18.2469,48.4004],[18.2406,48.3985],[18.2348,48.4014],[18.2352,48.3977],[18.2285,48.3949],[18.2219,48.3972],[18.2274,48.4038],[18.2395,48.4068]],[[18.2345,48.4061],[18.232,48.4043],[18.2384,48.4023],[18.2345,48.4061]],[[18.2303,48.4019],[18.2274,48.3986],[18.2305,48.399],[18.2303,48.4019]]]},"properties":{"Popis":"karpatsk\u00fd keuper: kremenn\u00e9 pieskovce, ark\u00f3zy, zlepence, \u00edlovit\u00e9 bridlice, dolomity","\u00datvar":"trias","Vek1":"mlad\u0161\u00ed trias","S\u00favrstvie":"-","FID":46994}},{"type":"Feature","geometry":{"type":"Polygon","coordinates":[[[18.1923,48.4052],[18.2018,48.4001],[18.1931,48.3988],[18.1923,48.4052]]]},"properties":{"Popis":"hrubozrnn\u00e9 biotitick\u00e9 granodiority a\u017e tonality, tektonodeforma\u010dne prepracovan\u00e9","\u00datvar":"kry\u0161talinikum","Vek1":"paleozoikum - herc\u00fdnske granitoidy (karb\u00f3n)","S\u00favrstvie":"-","FID":47159}},{"type":"Feature","geometry":{"type":"Polygon","coordinates":[[[18.1933,48.4049],[18.2038,48.4011],[18.2072,48.3944],[18.1942,48.3946],[18.2018,48.4005],[18.1933,48.4049]]]},"properties":{"Popis":"deluvi\u00e1lne sedimenty: preva\u017ene hlinito-kamenit\u00e9 (podradne pies\u010dito-kamenit\u00e9) svahoviny a sutiny","\u00datvar":"kvart\u00e9r","Vek1":"pleistoc\u00e9n - holoc\u00e9n","S\u00favrstvie":"-","FID":47183}},{"type":"Feature","geometry":{"type":"Polygon","coordinates":[[[18.1774,48.4047],[18.1982,48.3973],[18.1916,48.395],[18.1846,48.3974],[18.1803,48.3882],[18.159,48.39],[18.1644,48.3962],[18.1826,48.4018],[18.1736,48.4036],[18.1774,48.4047]]]},"properties":{"Popis":"l\u00fa\u017e\u0148ansk\u00e9 s\u00favrstvie: svetlosiv\u00e9, ru\u017eov\u00e9, \u010derven\u00e9 kremence, kremenn\u00e9 pieskovce, ark\u00f3zov\u00e9 pieskovce, konglomer\u00e1ty","\u00datvar":"trias","Vek1":"star\u0161\u00ed trias","S\u00favrstvie":"l\u00fa\u017e\u0148ansk\u00e9 s\u00favrstvie","FID":47212}},{"type":"Feature","geometry":{"type":"Polygon","coordinates":[[[18.197,48.4061],[18.2019,48.4028],[18.1922,48.4055],[18.197,48.4061]]]},"properties":{"Popis":"deluvi\u00e1lne sedimenty: preva\u017ene hlinito-kamenit\u00e9 (podradne pies\u010dito-kamenit\u00e9) svahoviny a sutiny","\u00datvar":"kvart\u00e9r","Vek1":"pleistoc\u00e9n - holoc\u00e9n","S\u00favrstvie":"-","FID":47287}},{"type":"Feature","geometry":{"type":"Polygon","coordinates":[[[18.2236,48.4078],[18.2346,48.4067],[18.2218,48.3997],[18.2236,48.4078]]]},"properties":{"Popis":"gutensteinsk\u00e9 s\u00favrstvie (gutensteinsk\u00e9 vrstvy) - gutensteinsk\u00e9 (annabergsk\u00e9) v\u00e1pence: tmavosiv\u00e9 a \u010dierne hrubolavicovit\u00e9, vrstevnat\u00e9, \u010derv\u00edkovit\u00e9 v\u00e1pence","\u00datvar":"trias","Vek1":"stredn\u00fd trias","S\u00favrstvie":"-","FID":47330}},{"type":"Feature","geometry":{"type":"Polygon","coordinates":[[[18.1995,48.4068],[18.1976,48.4065],[18.1989,48.4079],[18.1995,48.4068]]]},"properties":{"Popis":"deluvi\u00e1lne sedimenty: preva\u017ene hlinito-kamenit\u00e9 (podradne pies\u010dito-kamenit\u00e9) svahoviny a sutiny","\u00datvar":"kvart\u00e9r","Vek1":"pleistoc\u00e9n - holoc\u00e9n","S\u00favrstvie":"-","FID":47535}},{"type":"Feature","geometry":{"type":"Polygon","coordinates":[[[18.2177,48.4092],[18.2205,48.4074],[18.2127,48.4003],[18.2074,48.4032],[18.2177,48.4092]]]},"properties":{"Popis":"hrubozrnn\u00e9 biotitick\u00e9 granodiority a\u017e tonality, tektonodeforma\u010dne prepracovan\u00e9","\u00datvar":"kry\u0161talinikum","Vek1":"paleozoikum - herc\u00fdnske granitoidy (karb\u00f3n)","S\u00favrstvie":"-","FID":47571}},{"type":"Feature","geometry":{"type":"Polygon","coordinates":[[[18.2333,48.4107],[18.2325,48.4092],[18.2309,48.4101],[18.2333,48.4107]]]},"properties":{"Popis":"ramsausk\u00e9 dolomity: siv\u00e9 vrstevnat\u00e9 dolomity","\u00datvar":"trias","Vek1":"stredn\u00fd trias","S\u00favrstvie":"-","FID":47702}},{"type":"Feature","geometry":{"type":"Polygon","coordinates":[[[18.1977,48.4087],[18.1983,48.4066],[18.1947,48.4081],[18.1977,48.4087]]]},"properties":{"Popis":"leukokratn\u00e9 jemno a\u017e hrubozrnn\u00e9 biotiticko-muskovitick\u00e9 a\u017e muskovitick\u00e9 granity, \u010dasto s pegmatitoidn\u00fdm v\u00fdvojom","\u00datvar":"kry\u0161talinikum","Vek1":"paleozoikum - herc\u00fdnske granitoidy (star\u0161\u00ed karb\u00f3n)","S\u00favrstvie":"-","FID":47710}},{"type":"Feature","geometry":{"type":"Polygon","coordinates":[[[18.2248,48.4106],[18.239,48.4071],[18.2251,48.4072],[18.2248,48.4106]]]},"properties":{"Popis":"ramsausk\u00e9 dolomity: siv\u00e9 vrstevnat\u00e9 dolomity","\u00datvar":"trias","Vek1":"stredn\u00fd trias","S\u00favrstvie":"-","FID":47764}},{"type":"Feature","geometry":{"type":"Polygon","coordinates":[[[18.1929,48.4094],[18.2033,48.4019],[18.1981,48.4032],[18.2019,48.403],[18.1929,48.4094]]]},"properties":{"Popis":"fluvi\u00e1lne sedimenty: litofaci\u00e1lne ne\u010dlenen\u00e9 nivn\u00e9 hliny, alebo pies\u010dit\u00e9 a\u017e \u0161trkovit\u00e9 hliny dolinn\u00fdch n\u00edv a n\u00edv horsk\u00fdch potokov","\u00datvar":"kvart\u00e9r","Vek1":"holoc\u00e9n","S\u00favrstvie":"-","FID":47892}},{"type":"Feature","geometry":{"type":"Polygon","coordinates":[[[18.2042,48.4096],[18.2029,48.4031],[18.1989,48.4079],[18.2022,48.4064],[18.2042,48.4096]]]},"properties":{"Popis":"deluvi\u00e1lne sedimenty: preva\u017ene hlinito-kamenit\u00e9 (podradne pies\u010dito-kamenit\u00e9) svahoviny a sutiny","\u00datvar":"kvart\u00e9r","Vek1":"pleistoc\u00e9n - holoc\u00e9n","S\u00favrstvie":"-","FID":47915}},{"type":"Feature","geometry":{"type":"Polygon","coordinates":[[[18.2449,48.4124],[18.2577,48.4005],[18.2466,48.4095],[18.2449,48.4124]]]},"properties":{"Popis":"fluvi\u00e1lne sedimenty: litofaci\u00e1lne ne\u010dlenen\u00e9 nivn\u00e9 hliny, alebo pies\u010dit\u00e9 a\u017e \u0161trkovit\u00e9 hliny dolinn\u00fdch n\u00edv a n\u00edv horsk\u00fdch potokov","\u00datvar":"kvart\u00e9r","Vek1":"holoc\u00e9n","S\u00favrstvie":"-","FID":47955}},{"type":"Feature","geometry":{"type":"Polygon","coordinates":[[[18.1968,48.411],[18.1983,48.4086],[18.1923,48.4093],[18.1969,48.4049],[18.1922,48.4055],[18.1904,48.41],[18.1968,48.411]]]},"properties":{"Popis":"hrubozrnn\u00e9 biotitick\u00e9 granodiority a\u017e tonality","\u00datvar":"kry\u0161talinikum","Vek1":"paleozoikum - herc\u00fdnske granitoidy (mlad\u0161\u00ed karb\u00f3n)","S\u00favrstvie":"-","FID":48135}},{"type":"Feature","geometry":{"type":"Polygon","coordinates":[[[18.222,48.4134],[18.2224,48.4128],[18.2205,48.4126],[18.222,48.4134]]]},"properties":{"Popis":"leukokratn\u00e9 jemno a\u017e hrubozrnn\u00e9 biotiticko-muskovitick\u00e9 a\u017e muskovitick\u00e9 granity, \u010dasto s pegmatitoidn\u00fdm v\u00fdvojom","\u00datvar":"kry\u0161talinikum","Vek1":"paleozoikum - herc\u00fdnske granitoidy (star\u0161\u00ed karb\u00f3n)","S\u00favrstvie":"-","FID":48242}},{"type":"Feature","geometry":{"type":"Polygon","coordinates":[[[18.2354,48.4176],[18.239,48.4147],[18.2309,48.4101],[18.235,48.408],[18.2242,48.4106],[18.2218,48.3997],[18.2127,48.4003],[18.2205,48.4074],[18.2186,48.4099],[18.2354,48.4176]]]},"properties":{"Popis":"l\u00fa\u017e\u0148ansk\u00e9 s\u00favrstvie: svetlosiv\u00e9, ru\u017eov\u00e9, \u010derven\u00e9 kremence, kremenn\u00e9 pieskovce, ark\u00f3zov\u00e9 pieskovce, konglomer\u00e1ty","\u00datvar":"trias","Vek1":"star\u0161\u00ed trias","S\u00favrstvie":"l\u00fa\u017e\u0148ansk\u00e9 s\u00favrstvie","FID":48837}},{"type":"Feature","geometry":{"type":"Polygon","coordinates":[[[18.2027,48.4155],[18.2041,48.4103],[18.2013,48.4063],[18.1956,48.414],[18.2027,48.4155]]]},"properties":{"Popis":"hrubozrnn\u00e9 biotitick\u00e9 granodiority a\u017e tonality","\u00datvar":"kry\u0161talinikum","Vek1":"paleozoikum - herc\u00fdnske granitoidy (mlad\u0161\u00ed karb\u00f3n)","S\u00favrstvie":"-","FID":48903}},{"type":"Feature","geometry":{"type":"Polygon","coordinates":[[[18.1863,48.4153],[18.1931,48.3988],[18.1793,48.4046],[18.1731,48.4034],[18.1863,48.4153]]]},"properties":{"Popis":"strednozrnn\u00e9 biotitick\u00e9 granodiority a\u017e tonality, resp. kremenn\u00e9 diority, tektonodeforma\u010dne prepracovan\u00e9","\u00datvar":"kry\u0161talinikum","Vek1":"paleozoikum - herc\u00fdnske granitoidy (star\u0161\u00ed karb\u00f3n)","S\u00favrstvie":"-","FID":48974}},{"type":"Feature","geometry":{"type":"Polygon","coordinates":[[[18.2358,48.4201],[18.2398,48.4183],[18.2444,48.4129],[18.2358,48.4201]]]},"properties":{"Popis":"deluvi\u00e1lne sedimenty: preva\u017ene hlinito-kamenit\u00e9 (podradne pies\u010dito-kamenit\u00e9) svahoviny a sutiny","\u00datvar":"kvart\u00e9r","Vek1":"pleistoc\u00e9n - holoc\u00e9n","S\u00favrstvie":"-","FID":49343}},{"type":"Feature","geometry":{"type":"Polygon","coordinates":[[[18.1928,48.4183],[18.1965,48.4113],[18.1942,48.4097],[18.1872,48.4147],[18.1928,48.4183]]]},"properties":{"Popis":"leukokratn\u00e9 jemno a\u017e hrubozrnn\u00e9 biotiticko-muskovitick\u00e9 a\u017e muskovitick\u00e9 granity, \u010dasto s pegmatitoidn\u00fdm v\u00fdvojom","\u00datvar":"kry\u0161talinikum","Vek1":"paleozoikum - herc\u00fdnske granitoidy (star\u0161\u00ed karb\u00f3n)","S\u00favrstvie":"-","FID":49423}},{"type":"Feature","geometry":{"type":"Polygon","coordinates":[[[18.2213,48.4204],[18.2339,48.4175],[18.207,48.4043],[18.2046,48.4173],[18.2213,48.4204]],[[18.2212,48.4134],[18.2205,48.4126],[18.2224,48.4128],[18.2212,48.4134]]]},"properties":{"Popis":"hrubozrnn\u00e9 biotitick\u00e9 granodiority a\u017e tonality","\u00datvar":"kry\u0161talinikum","Vek1":"paleozoikum - herc\u00fdnske granitoidy (mlad\u0161\u00ed karb\u00f3n)","S\u00favrstvie":"-","FID":49449}},{"type":"Feature","geometry":{"type":"Polygon","coordinates":[[[18.2032,48.4217],[18.2049,48.4024],[18.2198,48.3922],[18.2267,48.3821],[18.224,48.3805],[18.2172,48.3912],[18.1999,48.4061],[18.2031,48.4032],[18.2032,48.4217]]]},"properties":{"Popis":"fluvi\u00e1lne sedimenty: litofaci\u00e1lne ne\u010dlenen\u00e9 nivn\u00e9 hliny, alebo pies\u010dit\u00e9 a\u017e \u0161trkovit\u00e9 hliny dolinn\u00fdch n\u00edv a n\u00edv horsk\u00fdch potokov","\u00datvar":"kvart\u00e9r","Vek1":"holoc\u00e9n","S\u00favrstvie":"-","FID":49880}},{"type":"Feature","geometry":{"type":"Polygon","coordinates":[[[18.1981,48.4218],[18.1994,48.4212],[18.1971,48.4213],[18.1981,48.4218]]]},"properties":{"Popis":"leukokratn\u00e9 jemno a\u017e hrubozrnn\u00e9 biotiticko-muskovitick\u00e9 a\u017e muskovitick\u00e9 granity, \u010dasto s pegmatitoidn\u00fdm v\u00fdvojom","\u00datvar":"kry\u0161talinikum","Vek1":"paleozoikum - herc\u00fdnske granitoidy (star\u0161\u00ed karb\u00f3n)","S\u00favrstvie":"-","FID":49975}},{"type":"Feature","geometry":{"type":"Polygon","coordinates":[[[18.2826,48.4267],[18.2932,48.4179],[18.2946,48.413],[18.2916,48.4077],[18.2847,48.4106],[18.2801,48.4041],[18.2716,48.4038],[18.2654,48.4147],[18.2826,48.4267]]]},"properties":{"Popis":"l\u00fa\u017e\u0148ansk\u00e9 s\u00favrstvie: svetlosiv\u00e9, ru\u017eov\u00e9, \u010derven\u00e9 kremence, kremenn\u00e9 pieskovce, ark\u00f3zov\u00e9 pieskovce, konglomer\u00e1ty","\u00datvar":"trias","Vek1":"star\u0161\u00ed trias","S\u00favrstvie":"l\u00fa\u017e\u0148ansk\u00e9 s\u00favrstvie","FID":49987}},{"type":"Feature","geometry":{"type":"Polygon","coordinates":[[[18.2071,48.4232],[18.2076,48.4216],[18.2066,48.4221],[18.2071,48.4232]]]},"properties":{"Popis":"leukokratn\u00e9 jemno a\u017e hrubozrnn\u00e9 biotiticko-muskovitick\u00e9 a\u017e muskovitick\u00e9 granity, \u010dasto s pegmatitoidn\u00fdm v\u00fdvojom","\u00datvar":"kry\u0161talinikum","Vek1":"paleozoikum - herc\u00fdnske granitoidy (star\u0161\u00ed karb\u00f3n)","S\u00favrstvie":"-","FID":50148}},{"type":"Feature","geometry":{"type":"Polygon","coordinates":[[[18.2771,48.4278],[18.2821,48.4268],[18.2681,48.4189],[18.2651,48.4129],[18.256,48.417],[18.2666,48.4266],[18.2771,48.4278]]]},"properties":{"Popis":"strednozrnn\u00e9 biotitick\u00e9 granodiority a\u017e tonality, resp. kremenn\u00e9 diority, tektonodeforma\u010dne prepracovan\u00e9","\u00datvar":"kry\u0161talinikum","Vek1":"paleozoikum - herc\u00fdnske granitoidy (star\u0161\u00ed karb\u00f3n)","S\u00favrstvie":"-","FID":50213}},{"type":"Feature","geometry":{"type":"Polygon","coordinates":[[[18.1858,48.4223],[18.1923,48.4187],[18.1872,48.4147],[18.1808,48.4193],[18.1858,48.4223]]]},"properties":{"Popis":"hrubozrnn\u00e9 biotitick\u00e9 granodiority a\u017e tonality, tektonodeforma\u010dne prepracovan\u00e9","\u00datvar":"kry\u0161talinikum","Vek1":"paleozoikum - herc\u00fdnske granitoidy (karb\u00f3n)","S\u00favrstvie":"-","FID":50225}},{"type":"Feature","geometry":{"type":"Polygon","coordinates":[[[18.2111,48.426],[18.2256,48.4242],[18.21,48.4242],[18.2152,48.4222],[18.2278,48.4235],[18.2349,48.4207],[18.2571,48.4002],[18.2306,48.3842],[18.2227,48.3854],[18.2184,48.3937],[18.2087,48.3974],[18.2049,48.4024],[18.2031,48.4221],[18.2057,48.4062],[18.2097,48.4007],[18.2221,48.3997],[18.227,48.3948],[18.2352,48.3977],[18.2348,48.4014],[18.2406,48.3985],[18.255,48.4008],[18.2325,48.4092],[18.2384,48.4165],[18.2249,48.4204],[18.2129,48.4198],[18.2072,48.4241],[18.2111,48.426]],[[18.2269,48.389],[18.2263,48.3881],[18.2278,48.387],[18.2269,48.389]]]},"properties":{"Popis":"deluvi\u00e1lne sedimenty: preva\u017ene hlinito-kamenit\u00e9 (podradne pies\u010dito-kamenit\u00e9) svahoviny a sutiny","\u00datvar":"kvart\u00e9r","Vek1":"pleistoc\u00e9n - holoc\u00e9n","S\u00favrstvie":"-","FID":50592}},{"type":"Feature","geometry":{"type":"Polygon","coordinates":[[[18.2581,48.429],[18.2632,48.4287],[18.264,48.4252],[18.25,48.4181],[18.254,48.4234],[18.2517,48.4277],[18.2581,48.429]]]},"properties":{"Popis":"gutensteinsk\u00e9 s\u00favrstvie (gutensteinsk\u00e9 vrstvy) - gutensteinsk\u00e9 (annabergsk\u00e9) v\u00e1pence: tmavosiv\u00e9 a \u010dierne hrubolavicovit\u00e9, vrstevnat\u00e9, \u010derv\u00edkovit\u00e9 v\u00e1pence","\u00datvar":"trias","Vek1":"stredn\u00fd trias","S\u00favrstvie":"-","FID":50646}},{"type":"Feature","geometry":{"type":"Polygon","coordinates":[[[18.1899,48.425],[18.1901,48.4245],[18.1881,48.4244],[18.1899,48.425]]]},"properties":{"Popis":"leukokratn\u00e9 jemno a\u017e hrubozrnn\u00e9 biotiticko-muskovitick\u00e9 a\u017e muskovitick\u00e9 granity, \u010dasto s pegmatitoidn\u00fdm v\u00fdvojom","\u00datvar":"kry\u0161talinikum","Vek1":"paleozoikum - herc\u00fdnske granitoidy (star\u0161\u00ed karb\u00f3n)","S\u00favrstvie":"-","FID":50648}},{"type":"Feature","geometry":{"type":"Polygon","coordinates":[[[18.256,48.4295],[18.2614,48.4289],[18.2526,48.4285],[18.256,48.4295]]]},"properties":{"Popis":"pestr\u00e9 \u00edlovito-pies\u010dit\u00e9 bridlice s vlo\u017ekami kremenn\u00fdch pieskovcov","\u00datvar":"trias","Vek1":"star\u0161\u00ed trias","S\u00favrstvie":"-","FID":50756}},{"type":"Feature","geometry":{"type":"Polygon","coordinates":[[[18.2065,48.4269],[18.2059,48.4249],[18.2044,48.4251],[18.2065,48.4269]]]},"properties":{"Popis":"leukokratn\u00e9 jemno a\u017e hrubozrnn\u00e9 biotiticko-muskovitick\u00e9 a\u017e muskovitick\u00e9 granity, \u010dasto s pegmatitoidn\u00fdm v\u00fdvojom","\u00datvar":"kry\u0161talinikum","Vek1":"paleozoikum - herc\u00fdnske granitoidy (star\u0161\u00ed karb\u00f3n)","S\u00favrstvie":"-","FID":50808}},{"type":"Feature","geometry":{"type":"Polygon","coordinates":[[[18.2696,48.4339],[18.2787,48.4289],[18.2653,48.428],[18.2696,48.4339]]]},"properties":{"Popis":"deluvi\u00e1lne sedimenty: preva\u017ene hlinito-kamenit\u00e9 (podradne pies\u010dito-kamenit\u00e9) svahoviny a sutiny","\u00datvar":"kvart\u00e9r","Vek1":"pleistoc\u00e9n - holoc\u00e9n","S\u00favrstvie":"-","FID":51502}},{"type":"Feature","geometry":{"type":"Polygon","coordinates":[[[18.2082,48.4304],[18.2093,48.4295],[18.2071,48.4294],[18.2082,48.4304]]]},"properties":{"Popis":"deluvi\u00e1lne sedimenty: preva\u017ene hlinito-kamenit\u00e9 (podradne pies\u010dito-kamenit\u00e9) svahoviny a sutiny","\u00datvar":"kvart\u00e9r","Vek1":"pleistoc\u00e9n - holoc\u00e9n","S\u00favrstvie":"-","FID":51533}},{"type":"Feature","geometry":{"type":"Polygon","coordinates":[[[18.2554,48.4338],[18.2593,48.4327],[18.2501,48.4299],[18.2554,48.4338]]]},"properties":{"Popis":"strednozrnn\u00e9 biotitick\u00e9 granodiority a\u017e tonality, resp. kremenn\u00e9 diority, tektonodeforma\u010dne prepracovan\u00e9","\u00datvar":"kry\u0161talinikum","Vek1":"paleozoikum - herc\u00fdnske granitoidy (star\u0161\u00ed karb\u00f3n)","S\u00favrstvie":"-","FID":51577}},{"type":"Feature","geometry":{"type":"Polygon","coordinates":[[[18.1872,48.432],[18.1922,48.4318],[18.1917,48.4296],[18.1839,48.4312],[18.1872,48.432]]]},"properties":{"Popis":"leukokratn\u00e9 jemno a\u017e hrubozrnn\u00e9 biotiticko-muskovitick\u00e9 a\u017e muskovitick\u00e9 granity, \u010dasto s pegmatitoidn\u00fdm v\u00fdvojom","\u00datvar":"kry\u0161talinikum","Vek1":"paleozoikum - herc\u00fdnske granitoidy (star\u0161\u00ed karb\u00f3n)","S\u00favrstvie":"-","FID":51992}},{"type":"Feature","geometry":{"type":"Polygon","coordinates":[[[18.237,48.4355],[18.237,48.4287],[18.2424,48.421],[18.2669,48.4122],[18.2716,48.4038],[18.2801,48.4041],[18.2847,48.4106],[18.2916,48.4077],[18.2948,48.4143],[18.2845,48.4261],[18.2653,48.4276],[18.2881,48.4263],[18.3029,48.4116],[18.2913,48.405],[18.2849,48.4082],[18.29,48.4045],[18.2739,48.3974],[18.262,48.3975],[18.2449,48.4154],[18.2326,48.4236],[18.237,48.4355]]]},"properties":{"Popis":"deluvi\u00e1lne sedimenty: preva\u017ene hlinito-kamenit\u00e9 (podradne pies\u010dito-kamenit\u00e9) svahoviny a sutiny","\u00datvar":"kvart\u00e9r","Vek1":"pleistoc\u00e9n - holoc\u00e9n","S\u00favrstvie":"-","FID":52169}},{"type":"Feature","geometry":{"type":"Polygon","coordinates":[[[18.2235,48.4369],[18.2314,48.4347],[18.236,48.4374],[18.2309,48.424],[18.2235,48.4369]]]},"properties":{"Popis":"deluvi\u00e1lne sedimenty: preva\u017ene hlinito-kamenit\u00e9 (podradne pies\u010dito-kamenit\u00e9) svahoviny a sutiny","\u00datvar":"kvart\u00e9r","Vek1":"pleistoc\u00e9n - holoc\u00e9n","S\u00favrstvie":"-","FID":52629}},{"type":"Feature","geometry":{"type":"Polygon","coordinates":[[[18.1903,48.4358],[18.1906,48.4349],[18.19,48.4345],[18.1903,48.4358]]]},"properties":{"Popis":"leukokratn\u00e9 jemno a\u017e hrubozrnn\u00e9 biotiticko-muskovitick\u00e9 a\u017e muskovitick\u00e9 granity, \u010dasto s pegmatitoidn\u00fdm v\u00fdvojom","\u00datvar":"kry\u0161talinikum","Vek1":"paleozoikum - herc\u00fdnske granitoidy (star\u0161\u00ed karb\u00f3n)","S\u00favrstvie":"-","FID":52733}},{"type":"Feature","geometry":{"type":"Polygon","coordinates":[[[18.282,48.4431],[18.2724,48.4332],[18.2663,48.4328],[18.2656,48.4241],[18.2584,48.418],[18.2491,48.4169],[18.24,48.4239],[18.282,48.4431]],[[18.2546,48.4295],[18.2514,48.4273],[18.254,48.4234],[18.2502,48.4179],[18.2643,48.4259],[18.2632,48.4287],[18.2546,48.4295]]]},"properties":{"Popis":"l\u00fa\u017e\u0148ansk\u00e9 s\u00favrstvie: svetlosiv\u00e9, ru\u017eov\u00e9, \u010derven\u00e9 kremence, kremenn\u00e9 pieskovce, ark\u00f3zov\u00e9 pieskovce, konglomer\u00e1ty","\u00datvar":"trias","Vek1":"star\u0161\u00ed trias","S\u00favrstvie":"l\u00fa\u017e\u0148ansk\u00e9 s\u00favrstvie","FID":53125}},{"type":"Feature","geometry":{"type":"Polygon","coordinates":[[[18.2825,48.4432],[18.2835,48.4405],[18.2769,48.4371],[18.2825,48.4432]]]},"properties":{"Popis":"leukokratn\u00e9 jemno a\u017e hrubozrnn\u00e9 biotiticko-muskovitick\u00e9 a\u017e muskovitick\u00e9 granity, \u010dasto s pegmatitoidn\u00fdm v\u00fdvojom","\u00datvar":"kry\u0161talinikum","Vek1":"paleozoikum - herc\u00fdnske granitoidy (star\u0161\u00ed karb\u00f3n)","S\u00favrstvie":"-","FID":53127}},{"type":"Feature","geometry":{"type":"Polygon","coordinates":[[[18.1831,48.4378],[18.1935,48.4331],[18.184,48.4316],[18.1857,48.4304],[18.1811,48.4257],[18.1766,48.4303],[18.1868,48.4327],[18.1765,48.4317],[18.1693,48.4366],[18.1831,48.4378]],[[18.19,48.4358],[18.1903,48.4345],[18.1906,48.4355],[18.19,48.4358]]]},"properties":{"Popis":"hrubozrnn\u00e9 biotitick\u00e9 granodiority a\u017e tonality, tektonodeforma\u010dne prepracovan\u00e9","\u00datvar":"kry\u0161talinikum","Vek1":"paleozoikum - herc\u00fdnske granitoidy (karb\u00f3n)","S\u00favrstvie":"-","FID":53201}},{"type":"Feature","geometry":{"type":"Polygon","coordinates":[[[18.2379,48.4416],[18.2423,48.4373],[18.237,48.4331],[18.2399,48.438],[18.237,48.4387],[18.2379,48.4416]]]},"properties":{"Popis":"hrubozrnn\u00e9 biotitick\u00e9 granodiority a\u017e tonality, tektonodeforma\u010dne prepracovan\u00e9","\u00datvar":"kry\u0161talinikum","Vek1":"paleozoikum - herc\u00fdnske granitoidy (karb\u00f3n)","S\u00favrstvie":"-","FID":53341}},{"type":"Feature","geometry":{"type":"Polygon","coordinates":[[[18.2816,48.4454],[18.2899,48.4409],[18.2905,48.4304],[18.2724,48.4332],[18.2835,48.4405],[18.2822,48.4432],[18.261,48.4331],[18.2528,48.4333],[18.24,48.4239],[18.2372,48.4283],[18.2395,48.4367],[18.2816,48.4454]]]},"properties":{"Popis":"strednozrnn\u00e9 biotitick\u00e9 granodiority a\u017e tonality, resp. kremenn\u00e9 diority","\u00datvar":"kry\u0161talinikum","Vek1":"paleozoikum - herc\u00fdnske granitoidy (mlad\u0161\u00ed karb\u00f3n)","S\u00favrstvie":"-","FID":53567}},{"type":"Feature","geometry":{"type":"Polygon","coordinates":[[[18.1914,48.4406],[18.1913,48.4378],[18.1894,48.4385],[18.1914,48.4406]]]},"properties":{"Popis":"siv\u00e9 pies\u010dito-krinoidov\u00e9 v\u00e1pence s \u010diernymi rohovcami","\u00datvar":"jura","Vek1":"star\u0161ia - stredn\u00e1 jura","S\u00favrstvie":"-","FID":53586}},{"type":"Feature","geometry":{"type":"Polygon","coordinates":[[[18.1909,48.4406],[18.189,48.4387],[18.1891,48.4399],[18.1909,48.4406]]]},"properties":{"Popis":"karpatsk\u00fd keuper: kremenn\u00e9 pieskovce, ark\u00f3zy, zlepence, \u00edlovit\u00e9 bridlice, dolomity","\u00datvar":"trias","Vek1":"mlad\u0161\u00ed trias","S\u00favrstvie":"-","FID":53588}},{"type":"Feature","geometry":{"type":"Polygon","coordinates":[[[18.2369,48.443],[18.2331,48.4349],[18.2224,48.4383],[18.2369,48.443]]]},"properties":{"Popis":"strednozrnn\u00e9 biotitick\u00e9 granodiority a\u017e tonality, resp. kremenn\u00e9 diority, tektonodeforma\u010dne prepracovan\u00e9","\u00datvar":"kry\u0161talinikum","Vek1":"paleozoikum - herc\u00fdnske granitoidy (star\u0161\u00ed karb\u00f3n)","S\u00favrstvie":"-","FID":53669}},{"type":"Feature","geometry":{"type":"Polygon","coordinates":[[[18.2463,48.4443],[18.2472,48.4433],[18.2457,48.4439],[18.2463,48.4443]]]},"properties":{"Popis":"leukokratn\u00e9 jemno a\u017e hrubozrnn\u00e9 biotiticko-muskovitick\u00e9 a\u017e muskovitick\u00e9 granity, \u010dasto s pegmatitoidn\u00fdm v\u00fdvojom","\u00datvar":"kry\u0161talinikum","Vek1":"paleozoikum - herc\u00fdnske granitoidy (star\u0161\u00ed karb\u00f3n)","S\u00favrstvie":"-","FID":53683}},{"type":"Feature","geometry":{"type":"Polygon","coordinates":[[[18.2198,48.4426],[18.2271,48.4255],[18.2054,48.4335],[18.2141,48.4355],[18.2198,48.4426]]]},"properties":{"Popis":"deluvi\u00e1lne sedimenty: preva\u017ene hlinito-kamenit\u00e9 (podradne pies\u010dito-kamenit\u00e9) svahoviny a sutiny","\u00datvar":"kvart\u00e9r","Vek1":"pleistoc\u00e9n - holoc\u00e9n","S\u00favrstvie":"-","FID":53743}},{"type":"Feature","geometry":{"type":"Polygon","coordinates":[[[18.2194,48.4433],[18.2286,48.4246],[18.2349,48.4207],[18.2103,48.4238],[18.2256,48.4242],[18.2013,48.4345],[18.2271,48.4255],[18.2194,48.4433]]]},"properties":{"Popis":"fluvi\u00e1lne sedimenty: litofaci\u00e1lne ne\u010dlenen\u00e9 nivn\u00e9 hliny, alebo pies\u010dit\u00e9 a\u017e \u0161trkovit\u00e9 hliny dolinn\u00fdch n\u00edv a n\u00edv horsk\u00fdch potokov","\u00datvar":"kvart\u00e9r","Vek1":"holoc\u00e9n","S\u00favrstvie":"-","FID":53908}},{"type":"Feature","geometry":{"type":"Polygon","coordinates":[[[18.2447,48.4452],[18.2455,48.4442],[18.2434,48.4452],[18.2447,48.4452]]]},"properties":{"Popis":"fluvi\u00e1lne sedimenty: litofaci\u00e1lne ne\u010dlenen\u00e9 nivn\u00e9 hliny, alebo pies\u010dit\u00e9 a\u017e \u0161trkovit\u00e9 hliny dolinn\u00fdch n\u00edv a n\u00edv horsk\u00fdch potokov","\u00datvar":"kvart\u00e9r","Vek1":"holoc\u00e9n","S\u00favrstvie":"-","FID":53957}},{"type":"Feature","geometry":{"type":"Polygon","coordinates":[[[18.2684,48.4472],[18.2665,48.4461],[18.2665,48.4473],[18.2684,48.4472]]]},"properties":{"Popis":"deluvi\u00e1lne sedimenty: preva\u017ene hlinito-kamenit\u00e9 (podradne pies\u010dito-kamenit\u00e9) svahoviny a sutiny","\u00datvar":"kvart\u00e9r","Vek1":"pleistoc\u00e9n - holoc\u00e9n","S\u00favrstvie":"-","FID":54042}},{"type":"Feature","geometry":{"type":"Polygon","coordinates":[[[18.2238,48.4441],[18.2218,48.4422],[18.2193,48.4437],[18.2238,48.4441]]]},"properties":{"Popis":"deluvi\u00e1lne sedimenty: preva\u017ene hlinito-kamenit\u00e9 (podradne pies\u010dito-kamenit\u00e9) svahoviny a sutiny","\u00datvar":"kvart\u00e9r","Vek1":"pleistoc\u00e9n - holoc\u00e9n","S\u00favrstvie":"-","FID":54070}},{"type":"Feature","geometry":{"type":"Polygon","coordinates":[[[18.2409,48.4465],[18.2431,48.4447],[18.2378,48.4433],[18.2409,48.4465]]]},"properties":{"Popis":"hrubozrnn\u00e9 biotitick\u00e9 granodiority a\u017e tonality","\u00datvar":"kry\u0161talinikum","Vek1":"paleozoikum - herc\u00fdnske granitoidy (mlad\u0161\u00ed karb\u00f3n)","S\u00favrstvie":"-","FID":54162}},{"type":"Feature","geometry":{"type":"Polygon","coordinates":[[[18.2296,48.446],[18.2279,48.4407],[18.2352,48.4453],[18.2366,48.4435],[18.2324,48.4398],[18.2223,48.4396],[18.2296,48.446]]]},"properties":{"Popis":"hrubozrnn\u00e9 biotitick\u00e9 granodiority a\u017e tonality, tektonodeforma\u010dne prepracovan\u00e9","\u00datvar":"kry\u0161talinikum","Vek1":"paleozoikum - herc\u00fdnske granitoidy (karb\u00f3n)","S\u00favrstvie":"-","FID":54230}},{"type":"Feature","geometry":{"type":"Polygon","coordinates":[[[18.2642,48.4481],[18.2653,48.4478],[18.2617,48.4472],[18.2642,48.4481]]]},"properties":{"Popis":"deluvi\u00e1lne sedimenty: preva\u017ene hlinito-kamenit\u00e9 (podradne pies\u010dito-kamenit\u00e9) svahoviny a sutiny","\u00datvar":"kvart\u00e9r","Vek1":"pleistoc\u00e9n - holoc\u00e9n","S\u00favrstvie":"-","FID":54240}},{"type":"Feature","geometry":{"type":"Polygon","coordinates":[[[18.2847,48.4493],[18.3042,48.4234],[18.3028,48.4155],[18.2886,48.4268],[18.2708,48.4335],[18.2911,48.4307],[18.2899,48.4409],[18.2847,48.4493]],[[18.2971,48.4262],[18.2976,48.4226],[18.3022,48.4229],[18.2971,48.4262]]]},"properties":{"Popis":"deluvi\u00e1lne sedimenty: preva\u017ene hlinito-kamenit\u00e9 (podradne pies\u010dito-kamenit\u00e9) svahoviny a sutiny","\u00datvar":"kvart\u00e9r","Vek1":"pleistoc\u00e9n - holoc\u00e9n","S\u00favrstvie":"-","FID":54263}},{"type":"Feature","geometry":{"type":"Polygon","coordinates":[[[18.2451,48.4476],[18.2505,48.445],[18.281,48.4457],[18.2423,48.4373],[18.2378,48.4433],[18.2455,48.4442],[18.2451,48.4476]],[[18.2457,48.4442],[18.2472,48.4433],[18.2466,48.4442],[18.2457,48.4442]]]},"properties":{"Popis":"strednozrnn\u00e9 biotitick\u00e9 granodiority a\u017e tonality, resp. kremenn\u00e9 diority, tektonodeforma\u010dne prepracovan\u00e9","\u00datvar":"kry\u0161talinikum","Vek1":"paleozoikum - herc\u00fdnske granitoidy (star\u0161\u00ed karb\u00f3n)","S\u00favrstvie":"-","FID":54288}},{"type":"Feature","geometry":{"type":"Polygon","coordinates":[[[18.2819,48.4504],[18.287,48.4432],[18.2778,48.4469],[18.2668,48.4459],[18.2819,48.4504]]]},"properties":{"Popis":"hrubozrnn\u00e9 biotitick\u00e9 granodiority a\u017e tonality, tektonodeforma\u010dne prepracovan\u00e9","\u00datvar":"kry\u0161talinikum","Vek1":"paleozoikum - herc\u00fdnske granitoidy (karb\u00f3n)","S\u00favrstvie":"-","FID":54405}},{"type":"Feature","geometry":{"type":"Polygon","coordinates":[[[18.1884,48.4449],[18.1897,48.4433],[18.1883,48.444],[18.1884,48.4449]]]},"properties":{"Popis":"karpatsk\u00fd keuper: kremenn\u00e9 pieskovce, ark\u00f3zy, zlepence, \u00edlovit\u00e9 bridlice, dolomity","\u00datvar":"trias","Vek1":"mlad\u0161\u00ed trias","S\u00favrstvie":"-","FID":54410}},{"type":"Feature","geometry":{"type":"Polygon","coordinates":[[[18.2831,48.4505],[18.2834,48.4499],[18.2822,48.4497],[18.2831,48.4505]]]},"properties":{"Popis":"l\u00fa\u017e\u0148ansk\u00e9 s\u00favrstvie: svetlosiv\u00e9, ru\u017eov\u00e9, \u010derven\u00e9 kremence, kremenn\u00e9 pieskovce, ark\u00f3zov\u00e9 pieskovce, konglomer\u00e1ty","\u00datvar":"trias","Vek1":"star\u0161\u00ed trias","S\u00favrstvie":"l\u00fa\u017e\u0148ansk\u00e9 s\u00favrstvie","FID":54431}},{"type":"Feature","geometry":{"type":"Polygon","coordinates":[[[18.2515,48.4488],[18.2524,48.4475],[18.2498,48.4478],[18.2515,48.4488]]]},"properties":{"Popis":"leukokratn\u00e9 jemno a\u017e hrubozrnn\u00e9 biotiticko-muskovitick\u00e9 a\u017e muskovitick\u00e9 granity, \u010dasto s pegmatitoidn\u00fdm v\u00fdvojom","\u00datvar":"kry\u0161talinikum","Vek1":"paleozoikum - herc\u00fdnske granitoidy (star\u0161\u00ed karb\u00f3n)","S\u00favrstvie":"-","FID":54452}},{"type":"Feature","geometry":{"type":"Polygon","coordinates":[[[18.2147,48.4466],[18.2191,48.4431],[18.2144,48.4358],[18.2013,48.4345],[18.2071,48.4294],[18.2243,48.4247],[18.2088,48.4257],[18.2073,48.4237],[18.2129,48.4198],[18.2046,48.4173],[18.2033,48.4222],[18.2028,48.4161],[18.1956,48.414],[18.1841,48.4235],[18.1963,48.4275],[18.1944,48.436],[18.2147,48.4466]],[[18.2059,48.427],[18.2046,48.425],[18.2062,48.4254],[18.2059,48.427]],[[18.1886,48.4244],[18.1902,48.4249],[18.189,48.4251],[18.1886,48.4244]],[[18.2066,48.4233],[18.2066,48.4221],[18.2079,48.4218],[18.2066,48.4233]],[[18.1979,48.4219],[18.1972,48.4212],[18.1994,48.4212],[18.1979,48.4219]]]},"properties":{"Popis":"hrubozrnn\u00e9 biotitick\u00e9 granodiority a\u017e tonality, tektonodeforma\u010dne prepracovan\u00e9","\u00datvar":"kry\u0161talinikum","Vek1":"paleozoikum - herc\u00fdnske granitoidy (karb\u00f3n)","S\u00favrstvie":"-","FID":54471}},{"type":"Feature","geometry":{"type":"Polygon","coordinates":[[[18.239,48.4483],[18.2436,48.4457],[18.2381,48.4451],[18.237,48.4387],[18.2399,48.438],[18.2326,48.4236],[18.266,48.3944],[18.2631,48.3932],[18.244,48.4147],[18.2313,48.4231],[18.239,48.4483]]]},"properties":{"Popis":"fluvi\u00e1lne sedimenty: litofaci\u00e1lne ne\u010dlenen\u00e9 nivn\u00e9 hliny, alebo pies\u010dit\u00e9 a\u017e \u0161trkovit\u00e9 hliny dolinn\u00fdch n\u00edv a n\u00edv horsk\u00fdch potokov","\u00datvar":"kvart\u00e9r","Vek1":"holoc\u00e9n","S\u00favrstvie":"-","FID":54481}},{"type":"Feature","geometry":{"type":"Polygon","coordinates":[[[18.1894,48.4455],[18.1903,48.4433],[18.1881,48.445],[18.1894,48.4455]]]},"properties":{"Popis":"siv\u00e9 pies\u010dito-krinoidov\u00e9 v\u00e1pence s \u010diernymi rohovcami","\u00datvar":"jura","Vek1":"star\u0161ia - stredn\u00e1 jura","S\u00favrstvie":"-","FID":54509}},{"type":"Feature","geometry":{"type":"Polygon","coordinates":[[[18.2318,48.4488],[18.2354,48.4456],[18.2279,48.4407],[18.2318,48.4488]]]},"properties":{"Popis":"leukokratn\u00e9 jemno a\u017e hrubozrnn\u00e9 biotiticko-muskovitick\u00e9 a\u017e muskovitick\u00e9 granity, \u010dasto s pegmatitoidn\u00fdm v\u00fdvojom","\u00datvar":"kry\u0161talinikum","Vek1":"paleozoikum - herc\u00fdnske granitoidy (star\u0161\u00ed karb\u00f3n)","S\u00favrstvie":"-","FID":54653}},{"type":"Feature","geometry":{"type":"Polygon","coordinates":[[[18.2552,48.4518],[18.2668,48.4459],[18.2505,48.445],[18.2447,48.4476],[18.246,48.4515],[18.2529,48.4475],[18.2552,48.4518]]]},"properties":{"Popis":"hrubozrnn\u00e9 biotitick\u00e9 granodiority a\u017e tonality, tektonodeforma\u010dne prepracovan\u00e9","\u00datvar":"kry\u0161talinikum","Vek1":"paleozoikum - herc\u00fdnske granitoidy (karb\u00f3n)","S\u00favrstvie":"-","FID":54942}},{"type":"Feature","geometry":{"type":"Polygon","coordinates":[[[18.2407,48.4515],[18.2458,48.4507],[18.2436,48.4457],[18.2391,48.4474],[18.2407,48.4515]]]},"properties":{"Popis":"hrubozrnn\u00e9 biotitick\u00e9 granodiority a\u017e tonality","\u00datvar":"kry\u0161talinikum","Vek1":"paleozoikum - herc\u00fdnske granitoidy (mlad\u0161\u00ed karb\u00f3n)","S\u00favrstvie":"-","FID":55009}},{"type":"Feature","geometry":{"type":"Polygon","coordinates":[[[18.2391,48.4517],[18.237,48.4437],[18.2313,48.449],[18.2246,48.444],[18.2317,48.4515],[18.2391,48.4517]]]},"properties":{"Popis":"hrubozrnn\u00e9 biotitick\u00e9 granodiority a\u017e tonality","\u00datvar":"kry\u0161talinikum","Vek1":"paleozoikum - herc\u00fdnske granitoidy (mlad\u0161\u00ed karb\u00f3n)","S\u00favrstvie":"-","FID":55102}},{"type":"Feature","geometry":{"type":"Polygon","coordinates":[[[18.2265,48.4513],[18.2224,48.4441],[18.2147,48.4466],[18.2265,48.4513]]]},"properties":{"Popis":"hrubozrnn\u00e9 biotitick\u00e9 granodiority a\u017e tonality","\u00datvar":"kry\u0161talinikum","Vek1":"paleozoikum - herc\u00fdnske granitoidy (mlad\u0161\u00ed karb\u00f3n)","S\u00favrstvie":"-","FID":55216}},{"type":"Feature","geometry":{"type":"Polygon","coordinates":[[[18.2011,48.4504],[18.2144,48.4469],[18.1944,48.436],[18.1963,48.4275],[18.1829,48.4243],[18.1811,48.4257],[18.1845,48.4299],[18.1917,48.4296],[18.1934,48.4328],[18.1894,48.4367],[18.2033,48.4425],[18.2011,48.4504]]]},"properties":{"Popis":"strednozrnn\u00e9 biotitick\u00e9 granodiority a\u017e tonality, resp. kremenn\u00e9 diority, tektonodeforma\u010dne prepracovan\u00e9","\u00datvar":"kry\u0161talinikum","Vek1":"paleozoikum - herc\u00fdnske granitoidy (star\u0161\u00ed karb\u00f3n)","S\u00favrstvie":"-","FID":55224}},{"type":"Feature","geometry":{"type":"Polygon","coordinates":[[[18.2282,48.452],[18.2312,48.4518],[18.2279,48.4501],[18.2282,48.452]]]},"properties":{"Popis":"hrubozrnn\u00e9 biotitick\u00e9 granodiority a\u017e tonality","\u00datvar":"kry\u0161talinikum","Vek1":"paleozoikum - herc\u00fdnske granitoidy (mlad\u0161\u00ed karb\u00f3n)","S\u00favrstvie":"-","FID":55234}},{"type":"Feature","geometry":{"type":"Polygon","coordinates":[[[18.2618,48.4544],[18.2713,48.4498],[18.2611,48.4514],[18.2618,48.4544]]]},"properties":{"Popis":"hrubozrnn\u00e9 biotitick\u00e9 granodiority a\u017e tonality, tektonodeforma\u010dne prepracovan\u00e9","\u00datvar":"kry\u0161talinikum","Vek1":"paleozoikum - herc\u00fdnske granitoidy (karb\u00f3n)","S\u00favrstvie":"-","FID":55323}},{"type":"Feature","geometry":{"type":"Polygon","coordinates":[[[18.2481,48.4552],[18.2482,48.4539],[18.2426,48.4544],[18.2481,48.4552]]]},"properties":{"Popis":"leukokratn\u00e9 jemno a\u017e hrubozrnn\u00e9 biotiticko-muskovitick\u00e9 a\u017e muskovitick\u00e9 granity, \u010dasto s pegmatitoidn\u00fdm v\u00fdvojom","\u00datvar":"kry\u0161talinikum","Vek1":"paleozoikum - herc\u00fdnske granitoidy (star\u0161\u00ed karb\u00f3n)","S\u00favrstvie":"-","FID":55595}},{"type":"Feature","geometry":{"type":"Polygon","coordinates":[[[18.2556,48.4561],[18.2561,48.4558],[18.2552,48.4565],[18.2556,48.4561]]]},"properties":{"Popis":"fluvi\u00e1lne sedimenty: litofaci\u00e1lne ne\u010dlenen\u00e9 nivn\u00e9 hliny, alebo pies\u010dit\u00e9 a\u017e \u0161trkovit\u00e9 hliny dolinn\u00fdch n\u00edv a n\u00edv horsk\u00fdch potokov","\u00datvar":"kvart\u00e9r","Vek1":"holoc\u00e9n","S\u00favrstvie":"-","FID":55780}},{"type":"Feature","geometry":{"type":"Polygon","coordinates":[[[18.2276,48.4561],[18.2279,48.4501],[18.2344,48.4557],[18.2218,48.4407],[18.2299,48.424],[18.2389,48.4484],[18.2313,48.4231],[18.2184,48.444],[18.2238,48.4441],[18.2276,48.4561]]]},"properties":{"Popis":"fluvi\u00e1lne sedimenty: litofaci\u00e1lne ne\u010dlenen\u00e9 nivn\u00e9 hliny, alebo pies\u010dit\u00e9 a\u017e \u0161trkovit\u00e9 hliny dolinn\u00fdch n\u00edv a n\u00edv horsk\u00fdch potokov","\u00datvar":"kvart\u00e9r","Vek1":"holoc\u00e9n","S\u00favrstvie":"-","FID":56008}},{"type":"Feature","geometry":{"type":"Polygon","coordinates":[[[18.2056,48.4545],[18.2125,48.4483],[18.2006,48.4506],[18.206,48.4519],[18.2056,48.4545]]]},"properties":{"Popis":"strednozrnn\u00e9 biotitick\u00e9 granodiority a\u017e tonality, resp. kremenn\u00e9 diority","\u00datvar":"kry\u0161talinikum","Vek1":"paleozoikum - herc\u00fdnske granitoidy (mlad\u0161\u00ed karb\u00f3n)","S\u00favrstvie":"-","FID":56023}},{"type":"Feature","geometry":{"type":"Polygon","coordinates":[[[18.1879,48.4535],[18.1936,48.444],[18.1894,48.4385],[18.1816,48.4385],[18.1768,48.4449],[18.1863,48.4432],[18.1779,48.4458],[18.1879,48.4535]],[[18.1887,48.4456],[18.1886,48.4436],[18.1905,48.4435],[18.1887,48.4456]]]},"properties":{"Popis":"gutensteinsk\u00e9 s\u00favrstvie (gutensteinsk\u00e9 vrstvy) - gutensteinsk\u00e9 (annabergsk\u00e9) v\u00e1pence: tmavosiv\u00e9 a \u010dierne hrubolavicovit\u00e9, vrstevnat\u00e9, \u010derv\u00edkovit\u00e9 v\u00e1pence","\u00datvar":"trias","Vek1":"stredn\u00fd trias","S\u00favrstvie":"-","FID":56036}},{"type":"Feature","geometry":{"type":"Polygon","coordinates":[[[18.2335,48.459],[18.2335,48.4566],[18.2301,48.4563],[18.2335,48.459]]]},"properties":{"Popis":"hrubozrnn\u00e9 biotitick\u00e9 granodiority a\u017e tonality, tektonodeforma\u010dne prepracovan\u00e9","\u00datvar":"kry\u0161talinikum","Vek1":"paleozoikum - herc\u00fdnske granitoidy (karb\u00f3n)","S\u00favrstvie":"-","FID":56517}},{"type":"Feature","geometry":{"type":"Polygon","coordinates":[[[18.2064,48.4577],[18.2171,48.4542],[18.2104,48.4513],[18.2034,48.4575],[18.2064,48.4577]]]},"properties":{"Popis":"deluvi\u00e1lne sedimenty: preva\u017ene hlinito-kamenit\u00e9 (podradne pies\u010dito-kamenit\u00e9) svahoviny a sutiny","\u00datvar":"kvart\u00e9r","Vek1":"pleistoc\u00e9n - holoc\u00e9n","S\u00favrstvie":"-","FID":56592}},{"type":"Feature","geometry":{"type":"Polygon","coordinates":[[[18.2508,48.4598],[18.2611,48.4546],[18.2611,48.4514],[18.2714,48.4493],[18.2654,48.4485],[18.2518,48.4545],[18.2622,48.4494],[18.2541,48.4523],[18.2491,48.4558],[18.2562,48.454],[18.2508,48.4598]]]},"properties":{"Popis":"deluvi\u00e1lne sedimenty: preva\u017ene hlinito-kamenit\u00e9 (podradne pies\u010dito-kamenit\u00e9) svahoviny a sutiny","\u00datvar":"kvart\u00e9r","Vek1":"pleistoc\u00e9n - holoc\u00e9n","S\u00favrstvie":"-","FID":56638}},{"type":"Feature","geometry":{"type":"Polygon","coordinates":[[[18.2503,48.4605],[18.2618,48.455],[18.2552,48.4565],[18.2503,48.4605]]]},"properties":{"Popis":"deluvi\u00e1lne sedimenty: preva\u017ene hlinito-kamenit\u00e9 (podradne pies\u010dito-kamenit\u00e9) svahoviny a sutiny","\u00datvar":"kvart\u00e9r","Vek1":"pleistoc\u00e9n - holoc\u00e9n","S\u00favrstvie":"-","FID":56639}},{"type":"Feature","geometry":{"type":"Polygon","coordinates":[[[18.2037,48.458],[18.206,48.4576],[18.2031,48.4579],[18.2037,48.458]]]},"properties":{"Popis":"fluvi\u00e1lne sedimenty: litofaci\u00e1lne ne\u010dlenen\u00e9 nivn\u00e9 hliny, alebo pies\u010dit\u00e9 a\u017e \u0161trkovit\u00e9 hliny dolinn\u00fdch n\u00edv a n\u00edv horsk\u00fdch potokov","\u00datvar":"kvart\u00e9r","Vek1":"holoc\u00e9n","S\u00favrstvie":"-","FID":56667}},{"type":"Feature","geometry":{"type":"Polygon","coordinates":[[[18.182,48.4574],[18.1872,48.4535],[18.1772,48.4471],[18.1749,48.4525],[18.182,48.4574]]]},"properties":{"Popis":"gutensteinsk\u00e9 s\u00favrstvie (gutensteinsk\u00e9 vrstvy) - gutensteinsk\u00e9 (annabergsk\u00e9) v\u00e1pence: tmavosiv\u00e9 a \u010dierne hrubolavicovit\u00e9, vrstevnat\u00e9, \u010derv\u00edkovit\u00e9 v\u00e1pence","\u00datvar":"trias","Vek1":"stredn\u00fd trias","S\u00favrstvie":"-","FID":56814}},{"type":"Feature","geometry":{"type":"Polygon","coordinates":[[[18.258,48.4619],[18.2634,48.4546],[18.2514,48.4599],[18.258,48.4619]]]},"properties":{"Popis":"hrubozrnn\u00e9 biotitick\u00e9 granodiority a\u017e tonality, tektonodeforma\u010dne prepracovan\u00e9","\u00datvar":"kry\u0161talinikum","Vek1":"paleozoikum - herc\u00fdnske granitoidy (karb\u00f3n)","S\u00favrstvie":"-","FID":56863}},{"type":"Feature","geometry":{"type":"Polygon","coordinates":[[[18.2813,48.4632],[18.2851,48.4587],[18.2838,48.4553],[18.2758,48.4549],[18.2688,48.4595],[18.2797,48.459],[18.2813,48.4632]]]},"properties":{"Popis":"deluvi\u00e1lne sedimenty: preva\u017ene hlinito-kamenit\u00e9 (podradne pies\u010dito-kamenit\u00e9) svahoviny a sutiny","\u00datvar":"kvart\u00e9r","Vek1":"pleistoc\u00e9n - holoc\u00e9n","S\u00favrstvie":"-","FID":56865}},{"type":"Feature","geometry":{"type":"Polygon","coordinates":[[[18.241,48.4612],[18.2498,48.4609],[18.239,48.46],[18.241,48.4612]]]},"properties":{"Popis":"hrubozrnn\u00e9 biotitick\u00e9 granodiority a\u017e tonality, tektonodeforma\u010dne prepracovan\u00e9","\u00datvar":"kry\u0161talinikum","Vek1":"paleozoikum - herc\u00fdnske granitoidy (karb\u00f3n)","S\u00favrstvie":"-","FID":56915}},{"type":"Feature","geometry":{"type":"Polygon","coordinates":[[[18.1928,48.4581],[18.2006,48.4534],[18.2027,48.4466],[18.2033,48.4425],[18.1973,48.4383],[18.1693,48.4366],[18.1604,48.4419],[18.1516,48.4412],[18.1544,48.4456],[18.1612,48.4478],[18.1534,48.4502],[18.1614,48.4545],[18.1774,48.4454],[18.1814,48.4387],[18.1913,48.4378],[18.1936,48.4449],[18.1877,48.4539],[18.1928,48.4581]],[[18.1631,48.4416],[18.1631,48.4433],[18.1597,48.4441],[18.1631,48.4416]]]},"properties":{"Popis":"l\u00fa\u017e\u0148ansk\u00e9 s\u00favrstvie: svetlosiv\u00e9, ru\u017eov\u00e9, \u010derven\u00e9 kremence, kremenn\u00e9 pieskovce, ark\u00f3zov\u00e9 pieskovce, konglomer\u00e1ty","\u00datvar":"trias","Vek1":"star\u0161\u00ed trias","S\u00favrstvie":"l\u00fa\u017e\u0148ansk\u00e9 s\u00favrstvie","FID":56916}},{"type":"Feature","geometry":{"type":"Polygon","coordinates":[[[18.2573,48.4628],[18.2575,48.4626],[18.2558,48.4621],[18.2573,48.4628]]]},"properties":{"Popis":"leukokratn\u00e9 jemno a\u017e hrubozrnn\u00e9 biotiticko-muskovitick\u00e9 a\u017e muskovitick\u00e9 granity, \u010dasto s pegmatitoidn\u00fdm v\u00fdvojom","\u00datvar":"kry\u0161talinikum","Vek1":"paleozoikum - herc\u00fdnske granitoidy (star\u0161\u00ed karb\u00f3n)","S\u00favrstvie":"-","FID":57039}},{"type":"Feature","geometry":{"type":"Polygon","coordinates":[[[18.2636,48.4635],[18.2623,48.4622],[18.2586,48.463],[18.2636,48.4635]]]},"properties":{"Popis":"leukokratn\u00e9 jemno a\u017e hrubozrnn\u00e9 biotiticko-muskovitick\u00e9 a\u017e muskovitick\u00e9 granity, \u010dasto s pegmatitoidn\u00fdm v\u00fdvojom","\u00datvar":"kry\u0161talinikum","Vek1":"paleozoikum - herc\u00fdnske granitoidy (star\u0161\u00ed karb\u00f3n)","S\u00favrstvie":"-","FID":57102}},{"type":"Feature","geometry":{"type":"Polygon","coordinates":[[[18.2639,48.4634],[18.2724,48.4532],[18.2654,48.4548],[18.26,48.4622],[18.2639,48.4634]]]},"properties":{"Popis":"hrubozrnn\u00e9 biotitick\u00e9 granodiority a\u017e tonality, tektonodeforma\u010dne prepracovan\u00e9","\u00datvar":"kry\u0161talinikum","Vek1":"paleozoikum - herc\u00fdnske granitoidy (karb\u00f3n)","S\u00favrstvie":"-","FID":57127}},{"type":"Feature","geometry":{"type":"Polygon","coordinates":[[[18.2556,48.4649],[18.2667,48.4539],[18.2715,48.4527],[18.2719,48.4565],[18.2829,48.4512],[18.2739,48.4494],[18.2661,48.4529],[18.2556,48.4649]]]},"properties":{"Popis":"deluvi\u00e1lne sedimenty: preva\u017ene hlinito-kamenit\u00e9 (podradne pies\u010dito-kamenit\u00e9) svahoviny a sutiny","\u00datvar":"kvart\u00e9r","Vek1":"pleistoc\u00e9n - holoc\u00e9n","S\u00favrstvie":"-","FID":57418}},{"type":"Feature","geometry":{"type":"Polygon","coordinates":[[[18.197,48.4614],[18.2017,48.4581],[18.1986,48.4589],[18.197,48.4614]]]},"properties":{"Popis":"strednozrnn\u00e9 biotitick\u00e9 granodiority a\u017e tonality, resp. kremenn\u00e9 diority, tektonodeforma\u010dne prepracovan\u00e9","\u00datvar":"kry\u0161talinikum","Vek1":"paleozoikum - herc\u00fdnske granitoidy (star\u0161\u00ed karb\u00f3n)","S\u00favrstvie":"-","FID":57474}},{"type":"Feature","geometry":{"type":"Polygon","coordinates":[[[18.196,48.4615],[18.2026,48.4562],[18.1952,48.4568],[18.196,48.4615]]]},"properties":{"Popis":"strednozrnn\u00e9 biotitick\u00e9 granodiority a\u017e tonality, resp. kremenn\u00e9 diority, tektonodeforma\u010dne prepracovan\u00e9","\u00datvar":"kry\u0161talinikum","Vek1":"paleozoikum - herc\u00fdnske granitoidy (star\u0161\u00ed karb\u00f3n)","S\u00favrstvie":"-","FID":57521}},{"type":"Feature","geometry":{"type":"Polygon","coordinates":[[[18.1952,48.4611],[18.1952,48.4568],[18.2051,48.4538],[18.2034,48.4575],[18.2062,48.4521],[18.1935,48.4571],[18.1952,48.4611]]]},"properties":{"Popis":"deluvi\u00e1lne sedimenty: preva\u017ene hlinito-kamenit\u00e9 (podradne pies\u010dito-kamenit\u00e9) svahoviny a sutiny","\u00datvar":"kvart\u00e9r","Vek1":"pleistoc\u00e9n - holoc\u00e9n","S\u00favrstvie":"-","FID":57537}},{"type":"Feature","geometry":{"type":"Polygon","coordinates":[[[18.1965,48.4624],[18.2051,48.4538],[18.1971,48.4594],[18.1965,48.4624]]]},"properties":{"Popis":"fluvi\u00e1lne sedimenty: litofaci\u00e1lne ne\u010dlenen\u00e9 nivn\u00e9 hliny, alebo pies\u010dit\u00e9 a\u017e \u0161trkovit\u00e9 hliny dolinn\u00fdch n\u00edv a n\u00edv horsk\u00fdch potokov","\u00datvar":"kvart\u00e9r","Vek1":"holoc\u00e9n","S\u00favrstvie":"-","FID":57667}},{"type":"Feature","geometry":{"type":"Polygon","coordinates":[[[18.1982,48.4625],[18.2031,48.4579],[18.1963,48.4628],[18.1982,48.4625]]]},"properties":{"Popis":"deluvi\u00e1lne sedimenty: preva\u017ene hlinito-kamenit\u00e9 (podradne pies\u010dito-kamenit\u00e9) svahoviny a sutiny","\u00datvar":"kvart\u00e9r","Vek1":"pleistoc\u00e9n - holoc\u00e9n","S\u00favrstvie":"-","FID":57806}},{"type":"Feature","geometry":{"type":"Polygon","coordinates":[[[18.2662,48.468],[18.2756,48.4662],[18.2818,48.4605],[18.2688,48.4595],[18.2637,48.4644],[18.2662,48.468]],[[18.2671,48.4661],[18.2669,48.4646],[18.2696,48.4648],[18.2671,48.4661]]]},"properties":{"Popis":"hrubozrnn\u00e9 biotitick\u00e9 granodiority a\u017e tonality, tektonodeforma\u010dne prepracovan\u00e9","\u00datvar":"kry\u0161talinikum","Vek1":"paleozoikum - herc\u00fdnske granitoidy (karb\u00f3n)","S\u00favrstvie":"-","FID":57886}},{"type":"Feature","geometry":{"type":"Polygon","coordinates":[[[18.2579,48.4703],[18.2756,48.4662],[18.2587,48.4681],[18.2598,48.4631],[18.2552,48.465],[18.2578,48.462],[18.252,48.4606],[18.2529,48.468],[18.2579,48.4703]]]},"properties":{"Popis":"hrubozrnn\u00e9 biotitick\u00e9 granodiority a\u017e tonality","\u00datvar":"kry\u0161talinikum","Vek1":"paleozoikum - herc\u00fdnske granitoidy (mlad\u0161\u00ed karb\u00f3n)","S\u00favrstvie":"-","FID":58431}},{"type":"Feature","geometry":{"type":"Polygon","coordinates":[[[18.2742,48.4711],[18.2851,48.4595],[18.2847,48.4506],[18.3055,48.4245],[18.307,48.4165],[18.2978,48.4088],[18.2956,48.4097],[18.3027,48.4122],[18.2881,48.4263],[18.2652,48.4278],[18.2787,48.4289],[18.2693,48.4347],[18.2886,48.4268],[18.3035,48.416],[18.3042,48.4234],[18.2847,48.4493],[18.2665,48.4473],[18.2518,48.4544],[18.2676,48.4481],[18.2714,48.4496],[18.2552,48.4565],[18.2634,48.4546],[18.2625,48.4576],[18.2734,48.4495],[18.2829,48.4512],[18.2611,48.4655],[18.2758,48.4549],[18.2838,48.4553],[18.2851,48.4587],[18.2817,48.463],[18.2626,48.4703],[18.2806,48.4645],[18.2742,48.4711]]]},"properties":{"Popis":"fluvi\u00e1lne sedimenty: litofaci\u00e1lne ne\u010dlenen\u00e9 nivn\u00e9 hliny, alebo pies\u010dit\u00e9 a\u017e \u0161trkovit\u00e9 hliny dolinn\u00fdch n\u00edv a n\u00edv horsk\u00fdch potokov","\u00datvar":"kvart\u00e9r","Vek1":"holoc\u00e9n","S\u00favrstvie":"-","FID":58526}},{"type":"Feature","geometry":{"type":"Polygon","coordinates":[[[18.1968,48.4676],[18.2043,48.461],[18.2037,48.458],[18.1945,48.4664],[18.1968,48.4676]]]},"properties":{"Popis":"deluvi\u00e1lne sedimenty: preva\u017ene hlinito-kamenit\u00e9 (podradne pies\u010dito-kamenit\u00e9) svahoviny a sutiny","\u00datvar":"kvart\u00e9r","Vek1":"pleistoc\u00e9n - holoc\u00e9n","S\u00favrstvie":"-","FID":58608}},{"type":"Feature","geometry":{"type":"Polygon","coordinates":[[[18.1999,48.468],[18.209,48.4611],[18.2091,48.4576],[18.2027,48.4586],[18.2043,48.461],[18.1972,48.4659],[18.1999,48.468]]]},"properties":{"Popis":"l\u00fa\u017e\u0148ansk\u00e9 s\u00favrstvie: svetlosiv\u00e9, ru\u017eov\u00e9, \u010derven\u00e9 kremence, kremenn\u00e9 pieskovce, ark\u00f3zov\u00e9 pieskovce, konglomer\u00e1ty","\u00datvar":"trias","Vek1":"star\u0161\u00ed trias","S\u00favrstvie":"l\u00fa\u017e\u0148ansk\u00e9 s\u00favrstvie","FID":58664}},{"type":"Feature","geometry":{"type":"Polygon","coordinates":[[[18.2753,48.4741],[18.2837,48.4628],[18.2869,48.4693],[18.2867,48.4559],[18.2753,48.4741]]]},"properties":{"Popis":"fluvi\u00e1lne sedimenty: litofaci\u00e1lne ne\u010dlenen\u00e9 nivn\u00e9 hliny, alebo pies\u010dit\u00e9 a\u017e \u0161trkovit\u00e9 hliny dolinn\u00fdch n\u00edv a n\u00edv horsk\u00fdch potokov","\u00datvar":"kvart\u00e9r","Vek1":"holoc\u00e9n","S\u00favrstvie":"-","FID":58949}},{"type":"Feature","geometry":{"type":"Polygon","coordinates":[[[18.2754,48.4744],[18.3051,48.4731],[18.3075,48.4708],[18.3008,48.4645],[18.3017,48.4605],[18.3138,48.4584],[18.3154,48.4555],[18.3063,48.4507],[18.3057,48.4571],[18.2942,48.4579],[18.2874,48.463],[18.2865,48.4696],[18.2859,48.4657],[18.2809,48.4655],[18.2792,48.4672],[18.2847,48.4732],[18.2754,48.4744]],[[18.2953,48.4699],[18.2931,48.4693],[18.2962,48.4693],[18.2953,48.4699]]]},"properties":{"Popis":"hrubozrnn\u00e9 biotitick\u00e9 granodiority a\u017e tonality, tektonodeforma\u010dne prepracovan\u00e9","\u00datvar":"kry\u0161talinikum","Vek1":"paleozoikum - herc\u00fdnske granitoidy (karb\u00f3n)","S\u00favrstvie":"-","FID":59001}},{"type":"Feature","geometry":{"type":"Polygon","coordinates":[[[18.1821,48.4701],[18.1921,48.4621],[18.1927,48.4585],[18.1872,48.4535],[18.1736,48.464],[18.1821,48.4701]]]},"properties":{"Popis":"l\u00fa\u017e\u0148ansk\u00e9 s\u00favrstvie: svetlosiv\u00e9, ru\u017eov\u00e9, \u010derven\u00e9 kremence, kremenn\u00e9 pieskovce, ark\u00f3zov\u00e9 pieskovce, konglomer\u00e1ty","\u00datvar":"trias","Vek1":"star\u0161\u00ed trias","S\u00favrstvie":"l\u00fa\u017e\u0148ansk\u00e9 s\u00favrstvie","FID":59162}},{"type":"Feature","geometry":{"type":"Polygon","coordinates":[[[18.2443,48.4911],[18.2547,48.4892],[18.269,48.4748],[18.2529,48.468],[18.25,48.4603],[18.2562,48.454],[18.2491,48.4558],[18.2547,48.452],[18.2533,48.4478],[18.246,48.4515],[18.2345,48.4502],[18.2317,48.4515],[18.2342,48.4559],[18.2305,48.4517],[18.2275,48.4522],[18.2274,48.4561],[18.2268,48.452],[18.2147,48.4466],[18.2084,48.4515],[18.2055,48.4553],[18.2104,48.4513],[18.2171,48.4544],[18.2098,48.4567],[18.2083,48.4605],[18.2125,48.4608],[18.1986,48.4706],[18.2047,48.4741],[18.2136,48.4744],[18.2134,48.4712],[18.2139,48.4745],[18.2214,48.4749],[18.2189,48.4699],[18.2252,48.4754],[18.2253,48.4809],[18.2305,48.4803],[18.2443,48.4911]],[[18.2462,48.4897],[18.2445,48.4884],[18.246,48.4889],[18.2462,48.4897]],[[18.2468,48.489],[18.2457,48.4875],[18.2475,48.489],[18.2468,48.489]],[[18.245,48.4834],[18.2436,48.4819],[18.2454,48.4831],[18.245,48.4834]],[[18.2552,48.4831],[18.2537,48.4819],[18.2555,48.4824],[18.2552,48.4831]],[[18.2395,48.4796],[18.2375,48.4789],[18.2406,48.4794],[18.2395,48.4796]],[[18.2539,48.4795],[18.2527,48.4781],[18.2539,48.4786],[18.2539,48.4795]],[[18.2298,48.4756],[18.2289,48.4746],[18.2306,48.4755],[18.2298,48.4756]],[[18.2238,48.474],[18.2224,48.4732],[18.2237,48.4734],[18.2238,48.474]],[[18.2255,48.4735],[18.2245,48.4725],[18.2257,48.4729],[18.2255,48.4735]],[[18.2274,48.4733],[18.2227,48.4701],[18.2251,48.4703],[18.2274,48.4733]],[[18.2419,48.4727],[18.2394,48.4717],[18.2426,48.4724],[18.2419,48.4727]],[[18.2379,48.4717],[18.2376,48.4725],[18.2361,48.471],[18.2379,48.4717]],[[18.2139,48.4696],[18.2127,48.4697],[18.213,48.4683],[18.2139,48.4696]],[[18.2207,48.4694],[18.2179,48.4678],[18.2217,48.4693],[18.2207,48.4694]],[[18.2332,48.4671],[18.2347,48.4634],[18.2356,48.4655],[18.2332,48.4671]],[[18.2152,48.4628],[18.2166,48.4639],[18.2146,48.463],[18.2152,48.4628]],[[18.2178,48.4639],[18.2177,48.4632],[18.2189,48.4644],[18.2178,48.4639]],[[18.2299,48.4651],[18.2317,48.4648],[18.2304,48.4662],[18.2299,48.4651]],[[18.2272,48.4623],[18.2274,48.4616],[18.2286,48.4612],[18.2272,48.4623]],[[18.2404,48.4612],[18.239,48.46],[18.2498,48.4609],[18.2404,48.4612]],[[18.2327,48.459],[18.2301,48.4563],[18.234,48.457],[18.2327,48.459]],[[18.2473,48.4552],[18.2426,48.4544],[18.2487,48.4543],[18.2473,48.4552]]]},"properties":{"Popis":"strednozrnn\u00e9 biotitick\u00e9 granodiority a\u017e tonality, resp. kremenn\u00e9 diority","\u00datvar":"kry\u0161talinikum","Vek1":"paleozoikum - herc\u00fdnske granitoidy (mlad\u0161\u00ed karb\u00f3n)","S\u00favrstvie":"-","FID":62142}}]}